{"v":"5.5.7","meta":{"g":"LottieFiles AE 0.1.20","a":"","k":"","d":"","tc":""},"fr":60,"ip":0,"op":165,"w":3240,"h":3240,"nm":"Frame 713","ddd":0,"assets":[{"id":"comp_0","layers":[{"ddd":0,"ind":1,"ty":4,"nm":"Vector 1","sr":1,"ks":{"o":{"a":0,"k":97,"ix":11},"r":{"a":1,"k":[{"i":{"x":[0.4],"y":[1]},"o":{"x":[0.167],"y":[0.167]},"t":0,"s":[0]},{"t":120,"s":[360]}],"ix":10},"p":{"a":1,"k":[{"i":{"x":0.833,"y":0.868},"o":{"x":0.167,"y":0.167},"t":0,"s":[1765.906,1760.499,0],"to":[154,45.333,0],"ti":[-265.333,-74,0]},{"i":{"x":0.6,"y":1},"o":{"x":0.167,"y":0.215},"t":33.846,"s":[2689.906,2032.499,0],"to":[265.333,74,0],"ti":[-111.333,-28.667,0]},{"t":73.333984375,"s":[3357.906,2204.499,0]}],"ix":2},"a":{"a":0,"k":[0,0,0],"ix":1},"s":{"a":1,"k":[{"i":{"x":[0.4,0.4,0.4],"y":[1,1,1]},"o":{"x":[0.167,0.167,0.167],"y":[-0.562,-0.562,-50.556]},"t":0,"s":[0,0,100]},{"t":91,"s":[90,90,100]}],"ix":6}},"ao":0,"shapes":[{"ty":"gr","it":[{"ind":0,"ty":"sh","ix":1,"ks":{"a":0,"k":{"i":[[0,0],[0,-16.797],[10.721,15.486]],"o":[[-63.614,-43.6],[0,24.467],[0,0]],"v":[[35.738,29.663],[20.728,-8.577],[-35.738,-29.663]],"c":false},"ix":2},"nm":"Path 1","mn":"ADBE Vector Shape - Group","hd":false},{"ty":"st","c":{"a":0,"k":[0.964705884457,0.772549033165,0.411764711142,1],"ix":3},"o":{"a":0,"k":100,"ix":4},"w":{"a":0,"k":7.59,"ix":5},"lc":2,"lj":2,"bm":0,"nm":"Stroke 1","mn":"ADBE Vector Graphic - Stroke","hd":false},{"ty":"tr","p":{"a":0,"k":[0,0],"ix":2},"a":{"a":0,"k":[0,0],"ix":1},"s":{"a":0,"k":[300,300],"ix":3},"r":{"a":0,"k":21,"ix":6},"o":{"a":0,"k":100,"ix":7},"sk":{"a":0,"k":0,"ix":4},"sa":{"a":0,"k":0,"ix":5},"nm":"Transform"}],"nm":"Vector 1","np":2,"cix":2,"bm":0,"ix":1,"mn":"ADBE Vector Group","hd":false}],"ip":0,"op":300,"st":0,"bm":0},{"ddd":0,"ind":2,"ty":4,"nm":"Vector 1","sr":1,"ks":{"o":{"a":0,"k":81,"ix":11},"r":{"a":1,"k":[{"i":{"x":[0.4],"y":[1]},"o":{"x":[0.167],"y":[0.167]},"t":0,"s":[0]},{"t":120,"s":[360]}],"ix":10},"p":{"a":1,"k":[{"i":{"x":0.833,"y":0.884},"o":{"x":0.167,"y":0.167},"t":0,"s":[1717.961,1766.218,0],"to":[-172.667,99.333,0],"ti":[306.667,-187.333,0]},{"i":{"x":0.6,"y":1},"o":{"x":0.167,"y":0.23},"t":33.846,"s":[681.961,2362.218,0],"to":[-306.667,187.333,0],"ti":[134,-88,0]},{"t":88,"s":[-122.039,2890.218,0]}],"ix":2},"a":{"a":0,"k":[0,0,0],"ix":1},"s":{"a":1,"k":[{"i":{"x":[0.4,0.4,0.4],"y":[1,1,1]},"o":{"x":[0.167,0.167,0.167],"y":[-0.562,-0.562,-50.556]},"t":0,"s":[0,0,100]},{"t":91,"s":[90,90,100]}],"ix":6}},"ao":0,"shapes":[{"ty":"gr","it":[{"ind":0,"ty":"sh","ix":1,"ks":{"a":0,"k":{"i":[[0,0],[0,-13.675],[8.729,12.608]],"o":[[-51.792,-35.498],[0,19.92],[0,0]],"v":[[29.096,24.15],[16.876,-6.983],[-29.096,-24.15]],"c":false},"ix":2},"nm":"Path 1","mn":"ADBE Vector Shape - Group","hd":false},{"ty":"st","c":{"a":0,"k":[0.964705884457,0.772549033165,0.411764711142,1],"ix":3},"o":{"a":0,"k":100,"ix":4},"w":{"a":0,"k":7.59,"ix":5},"lc":2,"lj":2,"bm":0,"nm":"Stroke 1","mn":"ADBE Vector Graphic - Stroke","hd":false},{"ty":"tr","p":{"a":0,"k":[0,0],"ix":2},"a":{"a":0,"k":[0,0],"ix":1},"s":{"a":0,"k":[300,300],"ix":3},"r":{"a":0,"k":-3,"ix":6},"o":{"a":0,"k":100,"ix":7},"sk":{"a":0,"k":0,"ix":4},"sa":{"a":0,"k":0,"ix":5},"nm":"Transform"}],"nm":"Vector 1","np":2,"cix":2,"bm":0,"ix":1,"mn":"ADBE Vector Group","hd":false}],"ip":0,"op":300,"st":0,"bm":0},{"ddd":0,"ind":3,"ty":4,"nm":"Vector 3","sr":1,"ks":{"o":{"a":0,"k":80,"ix":11},"r":{"a":1,"k":[{"i":{"x":[0.4],"y":[1]},"o":{"x":[0.167],"y":[0.167]},"t":0,"s":[0]},{"t":120,"s":[360]}],"ix":10},"p":{"a":1,"k":[{"i":{"x":0.833,"y":0.705},"o":{"x":0.167,"y":0.167},"t":0,"s":[1633.214,1733.089,0],"to":[72,11.333,0],"ti":[-278.667,-158,0]},{"i":{"x":0.6,"y":1},"o":{"x":0.167,"y":0.129},"t":33.846,"s":[2065.214,1801.089,0],"to":[278.667,158,0],"ti":[-206.667,-146.667,0]},{"t":83.48828125,"s":[3305.214,2681.089,0]}],"ix":2},"a":{"a":0,"k":[0,0,0],"ix":1},"s":{"a":1,"k":[{"i":{"x":[0.4,0.4,0.4],"y":[1,1,1]},"o":{"x":[0.167,0.167,0.167],"y":[0.562,0.562,50.556]},"t":0,"s":[0,0,100]},{"t":91,"s":[90,90,100]}],"ix":6}},"ao":0,"shapes":[{"ty":"gr","it":[{"ind":0,"ty":"sh","ix":1,"ks":{"a":0,"k":{"i":[[0,0],[0,-11.446],[7.306,10.553]],"o":[[-43.347,-29.71],[0,16.672],[0,0]],"v":[[24.352,20.212],[14.124,-5.845],[-24.352,-20.212]],"c":false},"ix":2},"nm":"Path 1","mn":"ADBE Vector Shape - Group","hd":false},{"ty":"st","c":{"a":0,"k":[0.898039221764,0.368627458811,0.35686275363,1],"ix":3},"o":{"a":0,"k":100,"ix":4},"w":{"a":0,"k":7.59,"ix":5},"lc":2,"lj":2,"bm":0,"nm":"Stroke 1","mn":"ADBE Vector Graphic - Stroke","hd":false},{"ty":"tr","p":{"a":0,"k":[0,0],"ix":2},"a":{"a":0,"k":[0,0],"ix":1},"s":{"a":0,"k":[300,300],"ix":3},"r":{"a":0,"k":58,"ix":6},"o":{"a":0,"k":100,"ix":7},"sk":{"a":0,"k":0,"ix":4},"sa":{"a":0,"k":0,"ix":5},"nm":"Transform"}],"nm":"Vector 3","np":2,"cix":2,"bm":0,"ix":1,"mn":"ADBE Vector Group","hd":false}],"ip":0,"op":300,"st":0,"bm":0},{"ddd":0,"ind":4,"ty":4,"nm":"Vector 2","sr":1,"ks":{"o":{"a":0,"k":100,"ix":11},"r":{"a":1,"k":[{"i":{"x":[0.4],"y":[1]},"o":{"x":[0.167],"y":[0.167]},"t":0,"s":[0]},{"t":120,"s":[360]}],"ix":10},"p":{"a":1,"k":[{"i":{"x":0.833,"y":0.87},"o":{"x":0.167,"y":0.167},"t":0,"s":[1727.814,1735.599,0],"to":[119.333,-8.667,0],"ti":[-270.667,6.667,0]},{"i":{"x":0.6,"y":1},"o":{"x":0.167,"y":0.196},"t":33.846,"s":[2443.814,1683.599,0],"to":[270.667,-6.667,0],"ti":[-151.333,-2,0]},{"t":98.154296875,"s":[3351.814,1695.599,0]}],"ix":2},"a":{"a":0,"k":[0,0,0],"ix":1},"s":{"a":1,"k":[{"i":{"x":[0.4,0.4,0.4],"y":[1,1,1]},"o":{"x":[0.167,0.167,0.167],"y":[0.562,0.562,50.556]},"t":0,"s":[0,0,100]},{"t":91,"s":[90,90,100]}],"ix":6}},"ao":0,"shapes":[{"ty":"gr","it":[{"ind":0,"ty":"sh","ix":1,"ks":{"a":0,"k":{"i":[[0,0],[0,-17.54],[11.196,16.172]],"o":[[-66.428,-45.53],[0,25.55],[0,0]],"v":[[37.319,30.975],[21.645,-8.957],[-37.319,-30.975]],"c":false},"ix":2},"nm":"Path 1","mn":"ADBE Vector Shape - Group","hd":false},{"ty":"st","c":{"a":0,"k":[0.305882364511,0.596078455448,0.960784316063,1],"ix":3},"o":{"a":0,"k":100,"ix":4},"w":{"a":0,"k":7.59,"ix":5},"lc":2,"lj":2,"bm":0,"nm":"Stroke 1","mn":"ADBE Vector Graphic - Stroke","hd":false},{"ty":"tr","p":{"a":0,"k":[0,0],"ix":2},"a":{"a":0,"k":[0,0],"ix":1},"s":{"a":0,"k":[300,300],"ix":3},"r":{"a":0,"k":26,"ix":6},"o":{"a":0,"k":100,"ix":7},"sk":{"a":0,"k":0,"ix":4},"sa":{"a":0,"k":0,"ix":5},"nm":"Transform"}],"nm":"Vector 2","np":2,"cix":2,"bm":0,"ix":1,"mn":"ADBE Vector Group","hd":false}],"ip":0,"op":300,"st":0,"bm":0},{"ddd":0,"ind":5,"ty":4,"nm":"Vector 1","sr":1,"ks":{"o":{"a":0,"k":84,"ix":11},"r":{"a":1,"k":[{"i":{"x":[0.4],"y":[1]},"o":{"x":[0.167],"y":[0.167]},"t":0,"s":[1474]},{"t":120,"s":[360]}],"ix":10},"p":{"a":1,"k":[{"i":{"x":0.6,"y":1},"o":{"x":0.167,"y":0.202},"t":33.846,"s":[1591.776,1727.904,0],"to":[-394.667,-746.667,0],"ti":[578.667,-749.333,0]},{"t":92.513671875,"s":[-176.224,1591.904,0]}],"ix":2},"a":{"a":0,"k":[0,0,0],"ix":1},"s":{"a":1,"k":[{"i":{"x":[0.4,0.4,0.4],"y":[1,1,1]},"o":{"x":[0.167,0.167,0.167],"y":[-0.562,-0.562,-50.556]},"t":0,"s":[0,0,100]},{"t":91,"s":[90,90,100]}],"ix":6}},"ao":0,"shapes":[{"ty":"gr","it":[{"ind":0,"ty":"sh","ix":1,"ks":{"a":0,"k":{"i":[[0,0],[0,-14.419],[9.203,13.294]],"o":[[-54.606,-37.427],[0,21.003],[0,0]],"v":[[30.678,25.462],[17.793,-7.363],[-30.678,-25.462]],"c":false},"ix":2},"nm":"Path 1","mn":"ADBE Vector Shape - Group","hd":false},{"ty":"st","c":{"a":0,"k":[0.964705884457,0.772549033165,0.411764711142,1],"ix":3},"o":{"a":0,"k":100,"ix":4},"w":{"a":0,"k":7.59,"ix":5},"lc":2,"lj":2,"bm":0,"nm":"Stroke 1","mn":"ADBE Vector Graphic - Stroke","hd":false},{"ty":"tr","p":{"a":0,"k":[0,0],"ix":2},"a":{"a":0,"k":[0,0],"ix":1},"s":{"a":0,"k":[300,300],"ix":3},"r":{"a":0,"k":78,"ix":6},"o":{"a":0,"k":100,"ix":7},"sk":{"a":0,"k":0,"ix":4},"sa":{"a":0,"k":0,"ix":5},"nm":"Transform"}],"nm":"Vector 1","np":2,"cix":2,"bm":0,"ix":1,"mn":"ADBE Vector Group","hd":false}],"ip":0,"op":300,"st":0,"bm":0},{"ddd":0,"ind":6,"ty":4,"nm":"Vector 3","sr":1,"ks":{"o":{"a":0,"k":100,"ix":11},"r":{"a":1,"k":[{"i":{"x":[0.4],"y":[1]},"o":{"x":[0.167],"y":[0.167]},"t":0,"s":[0]},{"t":120,"s":[360]}],"ix":10},"p":{"a":1,"k":[{"i":{"x":0.833,"y":0.802},"o":{"x":0.167,"y":0.167},"t":0,"s":[1670.802,1725.75,0],"to":[-83.333,88,0],"ti":[248.667,-260,0]},{"i":{"x":0.6,"y":1},"o":{"x":0.167,"y":0.151},"t":33.846,"s":[1170.802,2253.75,0],"to":[-248.667,260,0],"ti":[165.333,-172,0]},{"t":84.615234375,"s":[178.802,3285.75,0]}],"ix":2},"a":{"a":0,"k":[0,0,0],"ix":1},"s":{"a":1,"k":[{"i":{"x":[0.4,0.4,0.4],"y":[1,1,1]},"o":{"x":[0.167,0.167,0.167],"y":[0.562,0.562,50.556]},"t":0,"s":[0,0,100]},{"t":91,"s":[90,90,100]}],"ix":6}},"ao":0,"shapes":[{"ty":"gr","it":[{"ind":0,"ty":"sh","ix":1,"ks":{"a":0,"k":{"i":[[0,0],[0,-14.864],[9.488,13.705]],"o":[[-56.295,-38.584],[0,21.653],[0,0]],"v":[[31.627,26.25],[18.343,-7.59],[-31.627,-26.25]],"c":false},"ix":2},"nm":"Path 1","mn":"ADBE Vector Shape - Group","hd":false},{"ty":"st","c":{"a":0,"k":[0.898039221764,0.368627458811,0.35686275363,1],"ix":3},"o":{"a":0,"k":100,"ix":4},"w":{"a":0,"k":7.59,"ix":5},"lc":2,"lj":2,"bm":0,"nm":"Stroke 1","mn":"ADBE Vector Graphic - Stroke","hd":false},{"ty":"tr","p":{"a":0,"k":[0,0],"ix":2},"a":{"a":0,"k":[0,0],"ix":1},"s":{"a":0,"k":[300,300],"ix":3},"r":{"a":0,"k":0,"ix":6},"o":{"a":0,"k":100,"ix":7},"sk":{"a":0,"k":0,"ix":4},"sa":{"a":0,"k":0,"ix":5},"nm":"Transform"}],"nm":"Vector 3","np":2,"cix":2,"bm":0,"ix":1,"mn":"ADBE Vector Group","hd":false}],"ip":0,"op":300,"st":0,"bm":0},{"ddd":0,"ind":7,"ty":4,"nm":"Vector 2","sr":1,"ks":{"o":{"a":0,"k":100,"ix":11},"r":{"a":1,"k":[{"i":{"x":[0.4],"y":[1]},"o":{"x":[0.167],"y":[0.167]},"t":0,"s":[0]},{"t":120,"s":[360]}],"ix":10},"p":{"a":1,"k":[{"i":{"x":0.833,"y":0.852},"o":{"x":0.167,"y":0.167},"t":0,"s":[1662.802,1780.75,0],"to":[124,59.333,0],"ti":[-280,-192.667,0]},{"i":{"x":0.6,"y":1},"o":{"x":0.167,"y":0.179},"t":33.846,"s":[2406.802,2136.75,0],"to":[280,192.667,0],"ti":[-156,-133.333,0]},{"t":94.76953125,"s":[3342.802,2936.75,0]}],"ix":2},"a":{"a":0,"k":[0,0,0],"ix":1},"s":{"a":1,"k":[{"i":{"x":[0.4,0.4,0.4],"y":[1,1,1]},"o":{"x":[0.167,0.167,0.167],"y":[0.562,0.562,50.556]},"t":0,"s":[0,0,100]},{"t":91,"s":[90,90,100]}],"ix":6}},"ao":0,"shapes":[{"ty":"gr","it":[{"ind":0,"ty":"sh","ix":1,"ks":{"a":0,"k":{"i":[[0,0],[0,-14.864],[9.488,13.705]],"o":[[-56.295,-38.584],[0,21.653],[0,0]],"v":[[31.627,26.25],[18.343,-7.59],[-31.627,-26.25]],"c":false},"ix":2},"nm":"Path 1","mn":"ADBE Vector Shape - Group","hd":false},{"ty":"st","c":{"a":0,"k":[0.305882364511,0.596078455448,0.960784316063,1],"ix":3},"o":{"a":0,"k":100,"ix":4},"w":{"a":0,"k":7.59,"ix":5},"lc":2,"lj":2,"bm":0,"nm":"Stroke 1","mn":"ADBE Vector Graphic - Stroke","hd":false},{"ty":"tr","p":{"a":0,"k":[0,0],"ix":2},"a":{"a":0,"k":[0,0],"ix":1},"s":{"a":0,"k":[300,300],"ix":3},"r":{"a":0,"k":0,"ix":6},"o":{"a":0,"k":100,"ix":7},"sk":{"a":0,"k":0,"ix":4},"sa":{"a":0,"k":0,"ix":5},"nm":"Transform"}],"nm":"Vector 2","np":2,"cix":2,"bm":0,"ix":1,"mn":"ADBE Vector Group","hd":false}],"ip":0,"op":300,"st":0,"bm":0},{"ddd":0,"ind":8,"ty":4,"nm":"Rectangle 302","sr":1,"ks":{"o":{"a":0,"k":93,"ix":11},"r":{"a":1,"k":[{"i":{"x":[0.833],"y":[0.833]},"o":{"x":[0.27],"y":[0]},"t":0,"s":[-326]},{"t":135,"s":[1474]}],"ix":10},"p":{"a":1,"k":[{"i":{"x":0.833,"y":0.834},"o":{"x":0.167,"y":0.167},"t":0,"s":[1617.839,1715.363,0],"to":[80,108.667,0],"ti":[-185.333,-264.667,0]},{"i":{"x":0.6,"y":1},"o":{"x":0.167,"y":0.167},"t":33.846,"s":[2097.839,2367.363,0],"to":[185.333,264.667,0],"ti":[-105.333,-156,0]},{"t":81.23046875,"s":[2729.839,3303.363,0]}],"ix":2},"a":{"a":0,"k":[0,0,0],"ix":1},"s":{"a":1,"k":[{"i":{"x":[0.4,0.4,0.4],"y":[1,1,1]},"o":{"x":[0.167,0.167,0.167],"y":[0.562,0.562,50.556]},"t":0,"s":[0,0,100]},{"t":91,"s":[90,90,100]}],"ix":6}},"ao":0,"shapes":[{"ty":"gr","it":[{"ty":"rc","d":1,"s":{"a":0,"k":[27.36,13.368],"ix":2},"p":{"a":0,"k":[0,0],"ix":3},"r":{"a":0,"k":0,"ix":4},"nm":"Rectangle Path 1","mn":"ADBE Vector Shape - Rect","hd":false},{"ty":"fl","c":{"a":0,"k":[0.898039221764,0.368627458811,0.35686275363,1],"ix":4},"o":{"a":0,"k":100,"ix":5},"r":1,"bm":0,"nm":"Fill 1","mn":"ADBE Vector Graphic - Fill","hd":false},{"ty":"tr","p":{"a":0,"k":[0,0],"ix":2},"a":{"a":0,"k":[0,0],"ix":1},"s":{"a":0,"k":[300,300],"ix":3},"r":{"a":0,"k":-42,"ix":6},"o":{"a":0,"k":100,"ix":7},"sk":{"a":0,"k":0,"ix":4},"sa":{"a":0,"k":0,"ix":5},"nm":"Transform"}],"nm":"Rectangle 302","np":2,"cix":2,"bm":0,"ix":1,"mn":"ADBE Vector Group","hd":false}],"ip":0,"op":300,"st":0,"bm":0},{"ddd":0,"ind":9,"ty":4,"nm":"Rectangle 299","sr":1,"ks":{"o":{"a":0,"k":80,"ix":11},"r":{"a":1,"k":[{"i":{"x":[0.833],"y":[0.833]},"o":{"x":[0.27],"y":[0]},"t":0,"s":[-326]},{"t":135,"s":[1474]}],"ix":10},"p":{"a":1,"k":[{"i":{"x":0.833,"y":0.767},"o":{"x":0.167,"y":0.167},"t":0,"s":[1659.991,1695.633,0],"to":[70,42.667,0],"ti":[-120,-264.667,0]},{"i":{"x":0.6,"y":1},"o":{"x":0.167,"y":0.141},"t":33.846,"s":[2079.991,1951.633,0],"to":[120,264.667,0],"ti":[-50,-222,0]},{"t":88,"s":[2379.991,3283.633,0]}],"ix":2},"a":{"a":0,"k":[0,0,0],"ix":1},"s":{"a":1,"k":[{"i":{"x":[0.4,0.4,0.4],"y":[1,1,1]},"o":{"x":[0.167,0.167,0.167],"y":[0.562,0.562,50.556]},"t":0,"s":[0,0,100]},{"t":91,"s":[90,90,100]}],"ix":6}},"ao":0,"shapes":[{"ty":"gr","it":[{"ty":"rc","d":1,"s":{"a":0,"k":[16.394,24.86],"ix":2},"p":{"a":0,"k":[0,0],"ix":3},"r":{"a":0,"k":0,"ix":4},"nm":"Rectangle Path 1","mn":"ADBE Vector Shape - Rect","hd":false},{"ty":"fl","c":{"a":0,"k":[0.305882364511,0.596078455448,0.960784316063,1],"ix":4},"o":{"a":0,"k":100,"ix":5},"r":1,"bm":0,"nm":"Fill 1","mn":"ADBE Vector Graphic - Fill","hd":false},{"ty":"tr","p":{"a":0,"k":[0,0],"ix":2},"a":{"a":0,"k":[0,0],"ix":1},"s":{"a":0,"k":[300,300],"ix":3},"r":{"a":0,"k":66,"ix":6},"o":{"a":0,"k":100,"ix":7},"sk":{"a":0,"k":0,"ix":4},"sa":{"a":0,"k":0,"ix":5},"nm":"Transform"}],"nm":"Rectangle 299","np":2,"cix":2,"bm":0,"ix":1,"mn":"ADBE Vector Group","hd":false}],"ip":0,"op":300,"st":0,"bm":0},{"ddd":0,"ind":10,"ty":4,"nm":"Rectangle 302","sr":1,"ks":{"o":{"a":0,"k":80,"ix":11},"r":{"a":1,"k":[{"i":{"x":[0.833],"y":[0.833]},"o":{"x":[0.27],"y":[0]},"t":0,"s":[-326]},{"t":135,"s":[1474]}],"ix":10},"p":{"a":1,"k":[{"i":{"x":0.833,"y":0.855},"o":{"x":0.167,"y":0.167},"t":0,"s":[1617.639,1768.756,0],"to":[-77.333,103.333,0],"ti":[168.667,-251.333,0]},{"i":{"x":0.6,"y":1},"o":{"x":0.167,"y":0.183},"t":33.846,"s":[1153.639,2388.756,0],"to":[-168.667,251.333,0],"ti":[91.333,-148,0]},{"t":91.384765625,"s":[605.639,3276.756,0]}],"ix":2},"a":{"a":0,"k":[0,0,0],"ix":1},"s":{"a":1,"k":[{"i":{"x":[0.4,0.4,0.4],"y":[1,1,1]},"o":{"x":[0.167,0.167,0.167],"y":[0.562,0.562,50.556]},"t":0,"s":[0,0,100]},{"t":91,"s":[90,90,100]}],"ix":6}},"ao":0,"shapes":[{"ty":"gr","it":[{"ty":"rc","d":1,"s":{"a":0,"k":[16.162,7.896],"ix":2},"p":{"a":0,"k":[0,0],"ix":3},"r":{"a":0,"k":0,"ix":4},"nm":"Rectangle Path 1","mn":"ADBE Vector Shape - Rect","hd":false},{"ty":"fl","c":{"a":0,"k":[0.898039221764,0.368627458811,0.35686275363,1],"ix":4},"o":{"a":0,"k":100,"ix":5},"r":1,"bm":0,"nm":"Fill 1","mn":"ADBE Vector Graphic - Fill","hd":false},{"ty":"tr","p":{"a":0,"k":[0,0],"ix":2},"a":{"a":0,"k":[0,0],"ix":1},"s":{"a":0,"k":[300,300],"ix":3},"r":{"a":0,"k":-18,"ix":6},"o":{"a":0,"k":100,"ix":7},"sk":{"a":0,"k":0,"ix":4},"sa":{"a":0,"k":0,"ix":5},"nm":"Transform"}],"nm":"Rectangle 302","np":2,"cix":2,"bm":0,"ix":1,"mn":"ADBE Vector Group","hd":false}],"ip":0,"op":300,"st":0,"bm":0},{"ddd":0,"ind":11,"ty":4,"nm":"Rectangle 300","sr":1,"ks":{"o":{"a":0,"k":80,"ix":11},"r":{"a":1,"k":[{"i":{"x":[0.833],"y":[0.833]},"o":{"x":[0.27],"y":[0]},"t":0,"s":[-326]},{"t":135,"s":[1474]}],"ix":10},"p":{"a":1,"k":[{"i":{"x":0.833,"y":0.796},"o":{"x":0.167,"y":0.167},"t":0,"s":[1637.312,1834.389,0],"to":[-22,85.333,0],"ti":[27.333,-245.333,0]},{"i":{"x":0.6,"y":1},"o":{"x":0.167,"y":0.146},"t":33.846,"s":[1505.312,2346.389,0],"to":[-27.333,245.333,0],"ti":[5.333,-160,0]},{"t":77.845703125,"s":[1473.312,3306.389,0]}],"ix":2},"a":{"a":0,"k":[0,0,0],"ix":1},"s":{"a":1,"k":[{"i":{"x":[0.4,0.4,0.4],"y":[1,1,1]},"o":{"x":[0.167,0.167,0.167],"y":[0.562,0.562,50.556]},"t":0,"s":[0,0,100]},{"t":91,"s":[90,90,100]}],"ix":6}},"ao":0,"shapes":[{"ty":"gr","it":[{"ty":"rc","d":1,"s":{"a":0,"k":[15.574,15.574],"ix":2},"p":{"a":0,"k":[0,0],"ix":3},"r":{"a":0,"k":0,"ix":4},"nm":"Rectangle Path 1","mn":"ADBE Vector Shape - Rect","hd":false},{"ty":"fl","c":{"a":0,"k":[0.572549045086,0.803921580315,0.380392163992,1],"ix":4},"o":{"a":0,"k":100,"ix":5},"r":1,"bm":0,"nm":"Fill 1","mn":"ADBE Vector Graphic - Fill","hd":false},{"ty":"tr","p":{"a":0,"k":[0,0],"ix":2},"a":{"a":0,"k":[0,0],"ix":1},"s":{"a":0,"k":[300,300],"ix":3},"r":{"a":0,"k":79,"ix":6},"o":{"a":0,"k":100,"ix":7},"sk":{"a":0,"k":0,"ix":4},"sa":{"a":0,"k":0,"ix":5},"nm":"Transform"}],"nm":"Rectangle 300","np":2,"cix":2,"bm":0,"ix":1,"mn":"ADBE Vector Group","hd":false}],"ip":0,"op":300,"st":0,"bm":0},{"ddd":0,"ind":12,"ty":4,"nm":"Rectangle 299","sr":1,"ks":{"o":{"a":0,"k":80,"ix":11},"r":{"a":1,"k":[{"i":{"x":[0.833],"y":[0.833]},"o":{"x":[0.27],"y":[0]},"t":0,"s":[-326]},{"t":135,"s":[1474]}],"ix":10},"p":{"a":1,"k":[{"i":{"x":0.833,"y":0.844},"o":{"x":0.167,"y":0.167},"t":0,"s":[1620.835,1710.199,0],"to":[30.667,104,0],"ti":[-48.667,-259.333,0]},{"i":{"x":0.6,"y":1},"o":{"x":0.167,"y":0.174},"t":33.846,"s":[1804.835,2334.199,0],"to":[48.667,259.333,0],"ti":[-18,-155.333,0]},{"t":88,"s":[1912.835,3266.199,0]}],"ix":2},"a":{"a":0,"k":[0,0,0],"ix":1},"s":{"a":1,"k":[{"i":{"x":[0.4,0.4,0.4],"y":[1,1,1]},"o":{"x":[0.167,0.167,0.167],"y":[-0.562,-0.562,-50.556]},"t":0,"s":[0,0,100]},{"t":91,"s":[90,90,100]}],"ix":6}},"ao":0,"shapes":[{"ty":"gr","it":[{"ty":"rc","d":1,"s":{"a":0,"k":[27.6,41.852],"ix":2},"p":{"a":0,"k":[0,0],"ix":3},"r":{"a":0,"k":0,"ix":4},"nm":"Rectangle Path 1","mn":"ADBE Vector Shape - Rect","hd":false},{"ty":"fl","c":{"a":0,"k":[0.305882364511,0.596078455448,0.960784316063,1],"ix":4},"o":{"a":0,"k":100,"ix":5},"r":1,"bm":0,"nm":"Fill 1","mn":"ADBE Vector Graphic - Fill","hd":false},{"ty":"tr","p":{"a":0,"k":[0,0],"ix":2},"a":{"a":0,"k":[0,0],"ix":1},"s":{"a":0,"k":[300,300],"ix":3},"r":{"a":0,"k":33,"ix":6},"o":{"a":0,"k":100,"ix":7},"sk":{"a":0,"k":0,"ix":4},"sa":{"a":0,"k":0,"ix":5},"nm":"Transform"}],"nm":"Rectangle 299","np":2,"cix":2,"bm":0,"ix":1,"mn":"ADBE Vector Group","hd":false}],"ip":0,"op":300,"st":0,"bm":0},{"ddd":0,"ind":13,"ty":4,"nm":"Rectangle 299","sr":1,"ks":{"o":{"a":0,"k":82,"ix":11},"r":{"a":1,"k":[{"i":{"x":[0.833],"y":[0.833]},"o":{"x":[0.27],"y":[0]},"t":0,"s":[-326]},{"t":135,"s":[1474]}],"ix":10},"p":{"a":1,"k":[{"i":{"x":0.833,"y":0.86},"o":{"x":0.167,"y":0.167},"t":0,"s":[1658.285,1801.471,0],"to":[-125.333,50,0],"ti":[294.667,-116,0]},{"i":{"x":0.6,"y":1},"o":{"x":0.167,"y":0.187},"t":33.846,"s":[906.285,2101.471,0],"to":[-294.667,116,0],"ti":[169.333,-66,0]},{"t":94.76953125,"s":[-109.715,2497.471,0]}],"ix":2},"a":{"a":0,"k":[0,0,0],"ix":1},"s":{"a":1,"k":[{"i":{"x":[0.4,0.4,0.4],"y":[1,1,1]},"o":{"x":[0.167,0.167,0.167],"y":[-0.562,-0.562,-50.556]},"t":0,"s":[0,0,100]},{"t":91,"s":[90,90,100]}],"ix":6}},"ao":0,"shapes":[{"ty":"gr","it":[{"ty":"rc","d":1,"s":{"a":0,"k":[24.931,37.806],"ix":2},"p":{"a":0,"k":[0,0],"ix":3},"r":{"a":0,"k":0,"ix":4},"nm":"Rectangle Path 1","mn":"ADBE Vector Shape - Rect","hd":false},{"ty":"fl","c":{"a":0,"k":[0.305882364511,0.596078455448,0.960784316063,1],"ix":4},"o":{"a":0,"k":100,"ix":5},"r":1,"bm":0,"nm":"Fill 1","mn":"ADBE Vector Graphic - Fill","hd":false},{"ty":"tr","p":{"a":0,"k":[0,0],"ix":2},"a":{"a":0,"k":[0,0],"ix":1},"s":{"a":0,"k":[300,300],"ix":3},"r":{"a":0,"k":-64,"ix":6},"o":{"a":0,"k":100,"ix":7},"sk":{"a":0,"k":0,"ix":4},"sa":{"a":0,"k":0,"ix":5},"nm":"Transform"}],"nm":"Rectangle 299","np":2,"cix":2,"bm":0,"ix":1,"mn":"ADBE Vector Group","hd":false}],"ip":0,"op":300,"st":0,"bm":0},{"ddd":0,"ind":14,"ty":4,"nm":"Rectangle 299","sr":1,"ks":{"o":{"a":0,"k":74,"ix":11},"r":{"a":1,"k":[{"i":{"x":[0.833],"y":[0.833]},"o":{"x":[0.27],"y":[0]},"t":0,"s":[-326]},{"t":135,"s":[1474]}],"ix":10},"p":{"a":1,"k":[{"i":{"x":0.833,"y":0.818},"o":{"x":0.167,"y":0.167},"t":0,"s":[1611.375,1697.88,0],"to":[2,-0.667,0],"ti":[-225.944,30.811,0]},{"i":{"x":0.6,"y":1},"o":{"x":0.167,"y":0.158},"t":33.846,"s":[2311.375,1157.88,0],"to":[528,-72,0],"ti":[-56,-496,0]},{"t":83.48828125,"s":[3391.375,1997.88,0]}],"ix":2},"a":{"a":0,"k":[0,0,0],"ix":1},"s":{"a":1,"k":[{"i":{"x":[0.4,0.4,0.4],"y":[1,1,1]},"o":{"x":[0.167,0.167,0.167],"y":[-0.562,-0.562,-50.556]},"t":0,"s":[0,0,100]},{"t":91,"s":[90,90,100]}],"ix":6}},"ao":0,"shapes":[{"ty":"gr","it":[{"ty":"rc","d":1,"s":{"a":0,"k":[12.089,18.331],"ix":2},"p":{"a":0,"k":[0,0],"ix":3},"r":{"a":0,"k":0,"ix":4},"nm":"Rectangle Path 1","mn":"ADBE Vector Shape - Rect","hd":false},{"ty":"fl","c":{"a":0,"k":[0.305882364511,0.596078455448,0.960784316063,1],"ix":4},"o":{"a":0,"k":100,"ix":5},"r":1,"bm":0,"nm":"Fill 1","mn":"ADBE Vector Graphic - Fill","hd":false},{"ty":"tr","p":{"a":0,"k":[0,0],"ix":2},"a":{"a":0,"k":[0,0],"ix":1},"s":{"a":0,"k":[300,300],"ix":3},"r":{"a":0,"k":30,"ix":6},"o":{"a":0,"k":100,"ix":7},"sk":{"a":0,"k":0,"ix":4},"sa":{"a":0,"k":0,"ix":5},"nm":"Transform"}],"nm":"Rectangle 299","np":2,"cix":2,"bm":0,"ix":1,"mn":"ADBE Vector Group","hd":false}],"ip":0,"op":300,"st":0,"bm":0},{"ddd":0,"ind":15,"ty":4,"nm":"Rectangle 302","sr":1,"ks":{"o":{"a":0,"k":82,"ix":11},"r":{"a":1,"k":[{"i":{"x":[0.833],"y":[0.833]},"o":{"x":[0.27],"y":[0]},"t":0,"s":[-326]},{"t":135,"s":[1474]}],"ix":10},"p":{"a":1,"k":[{"i":{"x":0.833,"y":0.683},"o":{"x":0.167,"y":0.167},"t":0,"s":[1585.3,1746.765,0],"to":[2.667,0,0],"ti":[-345.527,113.794,0]},{"i":{"x":0.6,"y":1},"o":{"x":0.167,"y":0.129},"t":33.846,"s":[2145.3,1438.765,0],"to":[1000,-329.333,0],"ti":[56,-530.667,0]},{"t":89.12890625,"s":[3153.3,3374.765,0]}],"ix":2},"a":{"a":0,"k":[0,0,0],"ix":1},"s":{"a":1,"k":[{"i":{"x":[0.4,0.4,0.4],"y":[1,1,1]},"o":{"x":[0.167,0.167,0.167],"y":[0.562,0.562,50.556]},"t":0,"s":[0,0,100]},{"t":91,"s":[90,90,100]}],"ix":6}},"ao":0,"shapes":[{"ty":"gr","it":[{"ty":"rc","d":1,"s":{"a":0,"k":[16.56,8.091],"ix":2},"p":{"a":0,"k":[0,0],"ix":3},"r":{"a":0,"k":0,"ix":4},"nm":"Rectangle Path 1","mn":"ADBE Vector Shape - Rect","hd":false},{"ty":"fl","c":{"a":0,"k":[0.898039221764,0.368627458811,0.35686275363,1],"ix":4},"o":{"a":0,"k":100,"ix":5},"r":1,"bm":0,"nm":"Fill 1","mn":"ADBE Vector Graphic - Fill","hd":false},{"ty":"tr","p":{"a":0,"k":[0,0],"ix":2},"a":{"a":0,"k":[0,0],"ix":1},"s":{"a":0,"k":[300,300],"ix":3},"r":{"a":0,"k":-62,"ix":6},"o":{"a":0,"k":100,"ix":7},"sk":{"a":0,"k":0,"ix":4},"sa":{"a":0,"k":0,"ix":5},"nm":"Transform"}],"nm":"Rectangle 302","np":2,"cix":2,"bm":0,"ix":1,"mn":"ADBE Vector Group","hd":false}],"ip":0,"op":300,"st":0,"bm":0},{"ddd":0,"ind":16,"ty":4,"nm":"Rectangle 298","sr":1,"ks":{"o":{"a":0,"k":73,"ix":11},"r":{"a":1,"k":[{"i":{"x":[0.833],"y":[0.833]},"o":{"x":[0.27],"y":[0]},"t":0,"s":[-326]},{"t":135,"s":[1474]}],"ix":10},"p":{"a":1,"k":[{"i":{"x":0.833,"y":0.849},"o":{"x":0.167,"y":0.167},"t":0,"s":[1667.405,1760.327,0],"to":[-132.667,-14,0],"ti":[295.333,-33.333,0]},{"i":{"x":0.6,"y":1},"o":{"x":0.167,"y":0.179},"t":33.846,"s":[871.405,1676.327,0],"to":[-295.333,33.333,0],"ti":[162.667,-47.333,0]},{"t":84.615234375,"s":[-104.595,1960.327,0]}],"ix":2},"a":{"a":0,"k":[0,0,0],"ix":1},"s":{"a":1,"k":[{"i":{"x":[0.4,0.4,0.4],"y":[1,1,1]},"o":{"x":[0.167,0.167,0.167],"y":[-0.562,-0.562,-50.556]},"t":0,"s":[0,0,100]},{"t":91,"s":[90,90,100]}],"ix":6}},"ao":0,"shapes":[{"ty":"gr","it":[{"ty":"rc","d":1,"s":{"a":0,"k":[14.4,36],"ix":2},"p":{"a":0,"k":[0,0],"ix":3},"r":{"a":0,"k":0,"ix":4},"nm":"Rectangle Path 1","mn":"ADBE Vector Shape - Rect","hd":false},{"ty":"fl","c":{"a":0,"k":[0.698039233685,0.482352942228,0.905882358551,1],"ix":4},"o":{"a":0,"k":100,"ix":5},"r":1,"bm":0,"nm":"Fill 1","mn":"ADBE Vector Graphic - Fill","hd":false},{"ty":"tr","p":{"a":0,"k":[0,0],"ix":2},"a":{"a":0,"k":[0,0],"ix":1},"s":{"a":0,"k":[300,300],"ix":3},"r":{"a":0,"k":-21,"ix":6},"o":{"a":0,"k":100,"ix":7},"sk":{"a":0,"k":0,"ix":4},"sa":{"a":0,"k":0,"ix":5},"nm":"Transform"}],"nm":"Rectangle 298","np":2,"cix":2,"bm":0,"ix":1,"mn":"ADBE Vector Group","hd":false}],"ip":0,"op":300,"st":0,"bm":0},{"ddd":0,"ind":17,"ty":4,"nm":"Rectangle 298","sr":1,"ks":{"o":{"a":0,"k":71,"ix":11},"r":{"a":1,"k":[{"i":{"x":[0.833],"y":[0.833]},"o":{"x":[0.27],"y":[0]},"t":0,"s":[-326]},{"t":135,"s":[1474]}],"ix":10},"p":{"a":1,"k":[{"i":{"x":0.833,"y":0.524},"o":{"x":0.167,"y":0.167},"t":0,"s":[1651.278,1749.311,0],"to":[-12,46,0],"ti":[95.333,-258,0]},{"i":{"x":0.6,"y":1},"o":{"x":0.167,"y":0.102},"t":45.846,"s":[1579.278,2025.311,0],"to":[-95.333,258,0],"ti":[83.333,-212,0]},{"t":92.513671875,"s":[1079.278,3297.311,0]}],"ix":2},"a":{"a":0,"k":[0,0,0],"ix":1},"s":{"a":1,"k":[{"i":{"x":[0.4,0.4,0.4],"y":[1,1,1]},"o":{"x":[0.167,0.167,0.167],"y":[-0.562,-0.562,-50.556]},"t":0,"s":[0,0,100]},{"t":91,"s":[90,90,100]}],"ix":6}},"ao":0,"shapes":[{"ty":"gr","it":[{"ty":"rc","d":1,"s":{"a":0,"k":[14.4,36],"ix":2},"p":{"a":0,"k":[0,0],"ix":3},"r":{"a":0,"k":0,"ix":4},"nm":"Rectangle Path 1","mn":"ADBE Vector Shape - Rect","hd":false},{"ty":"fl","c":{"a":0,"k":[0.698039233685,0.482352942228,0.905882358551,1],"ix":4},"o":{"a":0,"k":100,"ix":5},"r":1,"bm":0,"nm":"Fill 1","mn":"ADBE Vector Graphic - Fill","hd":false},{"ty":"tr","p":{"a":0,"k":[0,0],"ix":2},"a":{"a":0,"k":[0,0],"ix":1},"s":{"a":0,"k":[300,300],"ix":3},"r":{"a":0,"k":-12,"ix":6},"o":{"a":0,"k":100,"ix":7},"sk":{"a":0,"k":0,"ix":4},"sa":{"a":0,"k":0,"ix":5},"nm":"Transform"}],"nm":"Rectangle 298","np":2,"cix":2,"bm":0,"ix":1,"mn":"ADBE Vector Group","hd":false}],"ip":0,"op":300,"st":0,"bm":0},{"ddd":0,"ind":18,"ty":4,"nm":"Rectangle 302","sr":1,"ks":{"o":{"a":0,"k":92,"ix":11},"r":{"a":1,"k":[{"i":{"x":[0.833],"y":[0.833]},"o":{"x":[0.27],"y":[0]},"t":0,"s":[-326]},{"t":135,"s":[1474]}],"ix":10},"p":{"a":1,"k":[{"i":{"x":0.833,"y":0.6},"o":{"x":0.167,"y":0.167},"t":0,"s":[1632.315,1761.285,0],"to":[-51.333,58,0],"ti":[279.333,-216.667,0]},{"i":{"x":0.6,"y":1},"o":{"x":0.167,"y":0.101},"t":45.846,"s":[1324.315,2109.285,0],"to":[-279.333,216.667,0],"ti":[228,-158.667,0]},{"t":87,"s":[-43.685,3061.285,0]}],"ix":2},"a":{"a":0,"k":[0,0,0],"ix":1},"s":{"a":1,"k":[{"i":{"x":[0.4,0.4,0.4],"y":[1,1,1]},"o":{"x":[0.167,0.167,0.167],"y":[0.562,0.562,50.556]},"t":0,"s":[0,0,100]},{"t":91,"s":[90,90,100]}],"ix":6}},"ao":0,"shapes":[{"ty":"gr","it":[{"ty":"rc","d":1,"s":{"a":0,"k":[17.76,8.677],"ix":2},"p":{"a":0,"k":[0,0],"ix":3},"r":{"a":0,"k":0,"ix":4},"nm":"Rectangle Path 1","mn":"ADBE Vector Shape - Rect","hd":false},{"ty":"fl","c":{"a":0,"k":[0.898039221764,0.368627458811,0.35686275363,1],"ix":4},"o":{"a":0,"k":100,"ix":5},"r":1,"bm":0,"nm":"Fill 1","mn":"ADBE Vector Graphic - Fill","hd":false},{"ty":"tr","p":{"a":0,"k":[0,0],"ix":2},"a":{"a":0,"k":[0,0],"ix":1},"s":{"a":0,"k":[300,300],"ix":3},"r":{"a":0,"k":-87,"ix":6},"o":{"a":0,"k":100,"ix":7},"sk":{"a":0,"k":0,"ix":4},"sa":{"a":0,"k":0,"ix":5},"nm":"Transform"}],"nm":"Rectangle 302","np":2,"cix":2,"bm":0,"ix":1,"mn":"ADBE Vector Group","hd":false}],"ip":0,"op":300,"st":0,"bm":0},{"ddd":0,"ind":19,"ty":4,"nm":"Rectangle 299","sr":1,"ks":{"o":{"a":0,"k":73,"ix":11},"r":{"a":1,"k":[{"i":{"x":[0.833],"y":[0.833]},"o":{"x":[0.27],"y":[0]},"t":0,"s":[-326]},{"t":135,"s":[1474]}],"ix":10},"p":{"a":1,"k":[{"i":{"x":0.833,"y":0.675},"o":{"x":0.167,"y":0.167},"t":0,"s":[1644.579,1766.114,0],"to":[-78.667,22,0],"ti":[279.333,-78.667,0]},{"i":{"x":0.6,"y":1},"o":{"x":0.167,"y":0.105},"t":45.846,"s":[1172.579,1898.114,0],"to":[-279.333,78.667,0],"ti":[267.333,-80.667,0]},{"i":{"x":0.6,"y":1},"o":{"x":0.167,"y":0},"t":83.488,"s":[-31.421,2238.114,0],"to":[-267.333,80.667,0],"ti":[66.667,-24,0]},{"t":116,"s":[-431.421,2382.114,0]}],"ix":2},"a":{"a":0,"k":[0,0,0],"ix":1},"s":{"a":1,"k":[{"i":{"x":[0.4,0.4,0.4],"y":[1,1,1]},"o":{"x":[0.167,0.167,0.167],"y":[-0.562,-0.562,-50.556]},"t":0,"s":[0,0,100]},{"t":91,"s":[90,90,100]}],"ix":6}},"ao":0,"shapes":[{"ty":"gr","it":[{"ty":"rc","d":1,"s":{"a":0,"k":[25.44,38.577],"ix":2},"p":{"a":0,"k":[0,0],"ix":3},"r":{"a":0,"k":0,"ix":4},"nm":"Rectangle Path 1","mn":"ADBE Vector Shape - Rect","hd":false},{"ty":"fl","c":{"a":0,"k":[0.305882364511,0.596078455448,0.960784316063,1],"ix":4},"o":{"a":0,"k":100,"ix":5},"r":1,"bm":0,"nm":"Fill 1","mn":"ADBE Vector Graphic - Fill","hd":false},{"ty":"tr","p":{"a":0,"k":[0,0],"ix":2},"a":{"a":0,"k":[0,0],"ix":1},"s":{"a":0,"k":[300,300],"ix":3},"r":{"a":0,"k":40,"ix":6},"o":{"a":0,"k":100,"ix":7},"sk":{"a":0,"k":0,"ix":4},"sa":{"a":0,"k":0,"ix":5},"nm":"Transform"}],"nm":"Rectangle 299","np":2,"cix":2,"bm":0,"ix":1,"mn":"ADBE Vector Group","hd":false}],"ip":0,"op":300,"st":0,"bm":0},{"ddd":0,"ind":20,"ty":4,"nm":"Rectangle 299","sr":1,"ks":{"o":{"a":0,"k":100,"ix":11},"r":{"a":1,"k":[{"i":{"x":[0.833],"y":[0.833]},"o":{"x":[0.27],"y":[0]},"t":0,"s":[-326]},{"t":135,"s":[1474]}],"ix":10},"p":{"a":1,"k":[{"i":{"x":0.833,"y":0.077},"o":{"x":0.167,"y":0.167},"t":0,"s":[1625.624,1695.75,0],"to":[2.667,0,0],"ti":[-295.55,150.229,0]},{"i":{"x":0.6,"y":1},"o":{"x":0.167,"y":0.085},"t":45.846,"s":[1917.624,1631.75,0],"to":[1445.333,-734.667,0],"ti":[362.667,-1221.333,0]},{"t":85,"s":[3533.624,2791.75,0]}],"ix":2},"a":{"a":0,"k":[0,0,0],"ix":1},"s":{"a":1,"k":[{"i":{"x":[0.4,0.4,0.4],"y":[1,1,1]},"o":{"x":[0.167,0.167,0.167],"y":[0.562,0.562,50.556]},"t":0,"s":[0,0,100]},{"t":91,"s":[90,90,100]}],"ix":6}},"ao":0,"shapes":[{"ty":"gr","it":[{"ty":"rc","d":1,"s":{"a":0,"k":[16.56,25.111],"ix":2},"p":{"a":0,"k":[0,0],"ix":3},"r":{"a":0,"k":0,"ix":4},"nm":"Rectangle Path 1","mn":"ADBE Vector Shape - Rect","hd":false},{"ty":"fl","c":{"a":0,"k":[0.305882364511,0.596078455448,0.960784316063,1],"ix":4},"o":{"a":0,"k":100,"ix":5},"r":1,"bm":0,"nm":"Fill 1","mn":"ADBE Vector Graphic - Fill","hd":false},{"ty":"tr","p":{"a":0,"k":[0,0],"ix":2},"a":{"a":0,"k":[0,0],"ix":1},"s":{"a":0,"k":[300,300],"ix":3},"r":{"a":0,"k":71,"ix":6},"o":{"a":0,"k":100,"ix":7},"sk":{"a":0,"k":0,"ix":4},"sa":{"a":0,"k":0,"ix":5},"nm":"Transform"}],"nm":"Rectangle 299","np":2,"cix":2,"bm":0,"ix":1,"mn":"ADBE Vector Group","hd":false}],"ip":0,"op":300,"st":0,"bm":0},{"ddd":0,"ind":21,"ty":4,"nm":"Rectangle 300","sr":1,"ks":{"o":{"a":0,"k":87,"ix":11},"r":{"a":1,"k":[{"i":{"x":[0.833],"y":[0.833]},"o":{"x":[0.27],"y":[0]},"t":0,"s":[-326]},{"t":135,"s":[1474]}],"ix":10},"p":{"a":1,"k":[{"i":{"x":0.833,"y":0.323},"o":{"x":0.167,"y":0.167},"t":0,"s":[1696.54,1811.43,0],"to":[10,8,0],"ti":[1.333,-246,0]},{"i":{"x":0.6,"y":1},"o":{"x":0.167,"y":0.091},"t":45.846,"s":[1756.54,1859.43,0],"to":[-1.333,246,0],"ti":[11.333,-238,0]},{"t":87,"s":[1688.54,3287.43,0]}],"ix":2},"a":{"a":0,"k":[0,0,0],"ix":1},"s":{"a":1,"k":[{"i":{"x":[0.4,0.4,0.4],"y":[1,1,1]},"o":{"x":[0.167,0.167,0.167],"y":[-0.562,-0.562,-50.556]},"t":0,"s":[0,0,100]},{"t":91,"s":[90,90,100]}],"ix":6}},"ao":0,"shapes":[{"ty":"gr","it":[{"ty":"rc","d":1,"s":{"a":0,"k":[15.12,15.12],"ix":2},"p":{"a":0,"k":[0,0],"ix":3},"r":{"a":0,"k":0,"ix":4},"nm":"Rectangle Path 1","mn":"ADBE Vector Shape - Rect","hd":false},{"ty":"fl","c":{"a":0,"k":[0.572549045086,0.803921580315,0.380392163992,1],"ix":4},"o":{"a":0,"k":100,"ix":5},"r":1,"bm":0,"nm":"Fill 1","mn":"ADBE Vector Graphic - Fill","hd":false},{"ty":"tr","p":{"a":0,"k":[0,0],"ix":2},"a":{"a":0,"k":[0,0],"ix":1},"s":{"a":0,"k":[300,300],"ix":3},"r":{"a":0,"k":85,"ix":6},"o":{"a":0,"k":100,"ix":7},"sk":{"a":0,"k":0,"ix":4},"sa":{"a":0,"k":0,"ix":5},"nm":"Transform"}],"nm":"Rectangle 300","np":2,"cix":2,"bm":0,"ix":1,"mn":"ADBE Vector Group","hd":false}],"ip":0,"op":300,"st":0,"bm":0},{"ddd":0,"ind":22,"ty":4,"nm":"Rectangle 298","sr":1,"ks":{"o":{"a":0,"k":70,"ix":11},"r":{"a":1,"k":[{"i":{"x":[0.833],"y":[0.833]},"o":{"x":[0.27],"y":[0]},"t":0,"s":[-326]},{"t":135,"s":[1474]}],"ix":10},"p":{"a":1,"k":[{"i":{"x":0.6,"y":1},"o":{"x":0.167,"y":0.159},"t":45.846,"s":[1585.269,1746.446,0],"to":[-538,268.667,0],"ti":[-382,-940.667,0]},{"t":86.873046875,"s":[1213.269,3286.446,0]}],"ix":2},"a":{"a":0,"k":[0,0,0],"ix":1},"s":{"a":1,"k":[{"i":{"x":[0.4,0.4,0.4],"y":[1,1,1]},"o":{"x":[0.167,0.167,0.167],"y":[-0.562,-0.562,-50.556]},"t":0,"s":[0,0,100]},{"t":91,"s":[90,90,100]}],"ix":6}},"ao":0,"shapes":[{"ty":"gr","it":[{"ty":"rc","d":1,"s":{"a":0,"k":[23.52,58.8],"ix":2},"p":{"a":0,"k":[0,0],"ix":3},"r":{"a":0,"k":0,"ix":4},"nm":"Rectangle Path 1","mn":"ADBE Vector Shape - Rect","hd":false},{"ty":"fl","c":{"a":0,"k":[0.698039233685,0.482352942228,0.905882358551,1],"ix":4},"o":{"a":0,"k":100,"ix":5},"r":1,"bm":0,"nm":"Fill 1","mn":"ADBE Vector Graphic - Fill","hd":false},{"ty":"tr","p":{"a":0,"k":[0,0],"ix":2},"a":{"a":0,"k":[0,0],"ix":1},"s":{"a":0,"k":[300,300],"ix":3},"r":{"a":0,"k":-4,"ix":6},"o":{"a":0,"k":100,"ix":7},"sk":{"a":0,"k":0,"ix":4},"sa":{"a":0,"k":0,"ix":5},"nm":"Transform"}],"nm":"Rectangle 298","np":2,"cix":2,"bm":0,"ix":1,"mn":"ADBE Vector Group","hd":false}],"ip":0,"op":300,"st":0,"bm":0},{"ddd":0,"ind":23,"ty":4,"nm":"Rectangle 302","sr":1,"ks":{"o":{"a":0,"k":92,"ix":11},"r":{"a":1,"k":[{"i":{"x":[0.833],"y":[0.833]},"o":{"x":[0.27],"y":[0]},"t":0,"s":[-326]},{"t":135,"s":[1474]}],"ix":10},"p":{"a":1,"k":[{"i":{"x":0.833,"y":0.143},"o":{"x":0.167,"y":0.167},"t":0,"s":[1594.833,1772.383,0],"to":[0,-2.667,0],"ti":[318.904,96.985,0]},{"i":{"x":0.6,"y":1},"o":{"x":0.167,"y":0.094},"t":40,"s":[1490.833,1704.383,0],"to":[-1148.667,-349.333,0],"ti":[240.667,-1238.667,0]},{"t":82,"s":[-241.167,2704.383,0]}],"ix":2},"a":{"a":0,"k":[0,0,0],"ix":1},"s":{"a":1,"k":[{"i":{"x":[0.4,0.4,0.4],"y":[1,1,1]},"o":{"x":[0.167,0.167,0.167],"y":[-0.562,-0.562,-50.556]},"t":0,"s":[0,0,100]},{"t":91,"s":[90,90,100]}],"ix":6}},"ao":0,"shapes":[{"ty":"gr","it":[{"ty":"rc","d":1,"s":{"a":0,"k":[26.16,12.782],"ix":2},"p":{"a":0,"k":[0,0],"ix":3},"r":{"a":0,"k":0,"ix":4},"nm":"Rectangle Path 1","mn":"ADBE Vector Shape - Rect","hd":false},{"ty":"fl","c":{"a":0,"k":[0.898039221764,0.368627458811,0.35686275363,1],"ix":4},"o":{"a":0,"k":100,"ix":5},"r":1,"bm":0,"nm":"Fill 1","mn":"ADBE Vector Graphic - Fill","hd":false},{"ty":"tr","p":{"a":0,"k":[0,0],"ix":2},"a":{"a":0,"k":[0,0],"ix":1},"s":{"a":0,"k":[300,300],"ix":3},"r":{"a":0,"k":-50,"ix":6},"o":{"a":0,"k":100,"ix":7},"sk":{"a":0,"k":0,"ix":4},"sa":{"a":0,"k":0,"ix":5},"nm":"Transform"}],"nm":"Rectangle 302","np":2,"cix":2,"bm":0,"ix":1,"mn":"ADBE Vector Group","hd":false}],"ip":0,"op":300,"st":0,"bm":0},{"ddd":0,"ind":24,"ty":4,"nm":"Rectangle 298","sr":1,"ks":{"o":{"a":0,"k":88,"ix":11},"r":{"a":1,"k":[{"i":{"x":[0.833],"y":[0.833]},"o":{"x":[0.27],"y":[0]},"t":0,"s":[-326]},{"t":135,"s":[1474]}],"ix":10},"p":{"a":1,"k":[{"i":{"x":0.563,"y":0.099},"o":{"x":0.167,"y":0.167},"t":0,"s":[1687.434,1828.899,0],"to":[0.221,-0.884,0],"ti":[35.42,88.547,0]},{"i":{"x":0.843,"y":0.746},"o":{"x":0.342,"y":0.201},"t":11,"s":[1677.457,1808.182,0],"to":[-71.432,-178.574,0],"ti":[187.473,79.398,0]},{"i":{"x":0.6,"y":1},"o":{"x":0.167,"y":0.111},"t":49,"s":[1185.434,1054.899,0],"to":[-1090.656,-461.91,0],"ti":[-108.667,-894,0]},{"t":103,"s":[-674.566,2986.899,0]}],"ix":2},"a":{"a":0,"k":[0,0,0],"ix":1},"s":{"a":1,"k":[{"i":{"x":[0.4,0.4,0.4],"y":[1,1,1]},"o":{"x":[0.167,0.167,0.167],"y":[0.562,0.562,50.556]},"t":0,"s":[0,0,100]},{"t":91,"s":[90,90,100]}],"ix":6}},"ao":0,"shapes":[{"ty":"gr","it":[{"ty":"rc","d":1,"s":{"a":0,"k":[21.12,52.8],"ix":2},"p":{"a":0,"k":[0,0],"ix":3},"r":{"a":0,"k":0,"ix":4},"nm":"Rectangle Path 1","mn":"ADBE Vector Shape - Rect","hd":false},{"ty":"fl","c":{"a":0,"k":[0.698039233685,0.482352942228,0.905882358551,1],"ix":4},"o":{"a":0,"k":100,"ix":5},"r":1,"bm":0,"nm":"Fill 1","mn":"ADBE Vector Graphic - Fill","hd":false},{"ty":"tr","p":{"a":0,"k":[0,0],"ix":2},"a":{"a":0,"k":[0,0],"ix":1},"s":{"a":0,"k":[300,300],"ix":3},"r":{"a":0,"k":-76,"ix":6},"o":{"a":0,"k":100,"ix":7},"sk":{"a":0,"k":0,"ix":4},"sa":{"a":0,"k":0,"ix":5},"nm":"Transform"}],"nm":"Rectangle 298","np":2,"cix":2,"bm":0,"ix":1,"mn":"ADBE Vector Group","hd":false}],"ip":0,"op":300,"st":0,"bm":0},{"ddd":0,"ind":25,"ty":4,"nm":"Rectangle 297","sr":1,"ks":{"o":{"a":0,"k":83,"ix":11},"r":{"a":1,"k":[{"i":{"x":[0.833],"y":[0.833]},"o":{"x":[0.27],"y":[0]},"t":0,"s":[-326]},{"t":135,"s":[1474]}],"ix":10},"p":{"a":1,"k":[{"i":{"x":0.562,"y":0.281},"o":{"x":0.167,"y":0.167},"t":0,"s":[1695.037,1825.459,0],"to":[0,-0.587,0],"ti":[-1.552,24.654,0]},{"i":{"x":0.843,"y":0.617},"o":{"x":0.355,"y":0.118},"t":11,"s":[1688.234,1817.455,0],"to":[2.858,-45.392,0],"ti":[8.601,85.685,0]},{"i":{"x":0.6,"y":1},"o":{"x":0.167,"y":0.117},"t":43,"s":[1675.037,1507.459,0],"to":[-127.414,-1269.339,0],"ti":[853.333,-517.333,0]},{"t":122,"s":[-374.963,1155.459,0]}],"ix":2},"a":{"a":0,"k":[0,0,0],"ix":1},"s":{"a":1,"k":[{"i":{"x":[0.4,0.4,0.4],"y":[1,1,1]},"o":{"x":[0.167,0.167,0.167],"y":[0.562,0.562,50.556]},"t":0,"s":[0,0,100]},{"t":91,"s":[90,90,100]}],"ix":6}},"ao":0,"shapes":[{"ty":"gr","it":[{"ty":"rc","d":1,"s":{"a":0,"k":[24.48,61.2],"ix":2},"p":{"a":0,"k":[0,0],"ix":3},"r":{"a":0,"k":0,"ix":4},"nm":"Rectangle Path 1","mn":"ADBE Vector Shape - Rect","hd":false},{"ty":"fl","c":{"a":0,"k":[0.698039233685,0.482352942228,0.905882358551,1],"ix":4},"o":{"a":0,"k":100,"ix":5},"r":1,"bm":0,"nm":"Fill 1","mn":"ADBE Vector Graphic - Fill","hd":false},{"ty":"tr","p":{"a":0,"k":[0,0],"ix":2},"a":{"a":0,"k":[0,0],"ix":1},"s":{"a":0,"k":[300,300],"ix":3},"r":{"a":0,"k":-6,"ix":6},"o":{"a":0,"k":100,"ix":7},"sk":{"a":0,"k":0,"ix":4},"sa":{"a":0,"k":0,"ix":5},"nm":"Transform"}],"nm":"Rectangle 297","np":2,"cix":2,"bm":0,"ix":1,"mn":"ADBE Vector Group","hd":false}],"ip":0,"op":300,"st":0,"bm":0},{"ddd":0,"ind":26,"ty":4,"nm":"Rectangle 299","sr":1,"ks":{"o":{"a":0,"k":100,"ix":11},"r":{"a":1,"k":[{"i":{"x":[0.833],"y":[0.833]},"o":{"x":[0.27],"y":[0]},"t":0,"s":[-326]},{"t":135,"s":[1474]}],"ix":10},"p":{"a":1,"k":[{"i":{"x":0.6,"y":1},"o":{"x":0.167,"y":0.14},"t":45.846,"s":[1724.993,1679.965,0],"to":[794.667,-671.333,0],"ti":[413.333,-2028.667,0]},{"t":110,"s":[3132.993,3291.965,0]}],"ix":2},"a":{"a":0,"k":[0,0,0],"ix":1},"s":{"a":1,"k":[{"i":{"x":[0.4,0.4,0.4],"y":[1,1,1]},"o":{"x":[0.167,0.167,0.167],"y":[0.562,0.562,50.556]},"t":0,"s":[0,0,100]},{"t":91,"s":[90,90,100]}],"ix":6}},"ao":0,"shapes":[{"ty":"gr","it":[{"ty":"rc","d":1,"s":{"a":0,"k":[24,36.393],"ix":2},"p":{"a":0,"k":[0,0],"ix":3},"r":{"a":0,"k":0,"ix":4},"nm":"Rectangle Path 1","mn":"ADBE Vector Shape - Rect","hd":false},{"ty":"fl","c":{"a":0,"k":[0.305882364511,0.596078455448,0.960784316063,1],"ix":4},"o":{"a":0,"k":100,"ix":5},"r":1,"bm":0,"nm":"Fill 1","mn":"ADBE Vector Graphic - Fill","hd":false},{"ty":"tr","p":{"a":0,"k":[0,0],"ix":2},"a":{"a":0,"k":[0,0],"ix":1},"s":{"a":0,"k":[300,300],"ix":3},"r":{"a":0,"k":21.416,"ix":6},"o":{"a":0,"k":100,"ix":7},"sk":{"a":0,"k":0,"ix":4},"sa":{"a":0,"k":0,"ix":5},"nm":"Transform"}],"nm":"Rectangle 299","np":2,"cix":2,"bm":0,"ix":1,"mn":"ADBE Vector Group","hd":false}],"ip":0,"op":300,"st":0,"bm":0},{"ddd":0,"ind":27,"ty":4,"nm":"Rectangle 300","sr":1,"ks":{"o":{"a":0,"k":100,"ix":11},"r":{"a":1,"k":[{"i":{"x":[0.833],"y":[0.833]},"o":{"x":[0.27],"y":[0]},"t":0,"s":[-326]},{"t":135,"s":[1474]}],"ix":10},"p":{"a":1,"k":[{"i":{"x":0.833,"y":0.645},"o":{"x":0.167,"y":0.167},"t":0,"s":[1680.923,1733,0],"to":[-2,-2,0],"ti":[169.426,206.463,0]},{"i":{"x":0.6,"y":1},"o":{"x":0.167,"y":0.122},"t":41,"s":[1396.923,1437,0],"to":[-430,-524,0],"ti":[474,-264,0]},{"t":101,"s":[-199.077,1293,0]}],"ix":2},"a":{"a":0,"k":[0,0,0],"ix":1},"s":{"a":1,"k":[{"i":{"x":[0.4,0.4,0.4],"y":[1,1,1]},"o":{"x":[0.167,0.167,0.167],"y":[0.562,0.562,50.556]},"t":0,"s":[0,0,100]},{"t":91,"s":[90,90,100]}],"ix":6}},"ao":0,"shapes":[{"ty":"gr","it":[{"ty":"rc","d":1,"s":{"a":0,"k":[24,24],"ix":2},"p":{"a":0,"k":[0,0],"ix":3},"r":{"a":0,"k":0,"ix":4},"nm":"Rectangle Path 1","mn":"ADBE Vector Shape - Rect","hd":false},{"ty":"fl","c":{"a":0,"k":[0.572549045086,0.803921580315,0.380392163992,1],"ix":4},"o":{"a":0,"k":100,"ix":5},"r":1,"bm":0,"nm":"Fill 1","mn":"ADBE Vector Graphic - Fill","hd":false},{"ty":"tr","p":{"a":0,"k":[0,0],"ix":2},"a":{"a":0,"k":[0,0],"ix":1},"s":{"a":0,"k":[300,300],"ix":3},"r":{"a":0,"k":0,"ix":6},"o":{"a":0,"k":100,"ix":7},"sk":{"a":0,"k":0,"ix":4},"sa":{"a":0,"k":0,"ix":5},"nm":"Transform"}],"nm":"Rectangle 300","np":2,"cix":2,"bm":0,"ix":1,"mn":"ADBE Vector Group","hd":false}],"ip":0,"op":300,"st":0,"bm":0},{"ddd":0,"ind":28,"ty":4,"nm":"Rectangle 302","sr":1,"ks":{"o":{"a":0,"k":100,"ix":11},"r":{"a":1,"k":[{"i":{"x":[0.833],"y":[0.833]},"o":{"x":[0.27],"y":[0]},"t":0,"s":[-326]},{"t":135,"s":[1474]}],"ix":10},"p":{"a":1,"k":[{"i":{"x":0.833,"y":0.664},"o":{"x":0.167,"y":0.167},"t":0,"s":[1584.512,1722.038,0],"to":[0.667,-2.667,0],"ti":[151.363,251.495,0]},{"i":{"x":0.6,"y":1},"o":{"x":0.167,"y":0.115},"t":49,"s":[1568.512,1174.038,0],"to":[-303.333,-504,0],"ti":[379.333,-128,0]},{"t":104,"s":[-155.488,814.038,0]}],"ix":2},"a":{"a":0,"k":[0,0,0],"ix":1},"s":{"a":1,"k":[{"i":{"x":[0.4,0.4,0.4],"y":[1,1,1]},"o":{"x":[0.167,0.167,0.167],"y":[0.562,0.562,50.556]},"t":0,"s":[0,0,100]},{"t":91,"s":[90,90,100]}],"ix":6}},"ao":0,"shapes":[{"ty":"gr","it":[{"ty":"rc","d":1,"s":{"a":0,"k":[24,11.726],"ix":2},"p":{"a":0,"k":[0,0],"ix":3},"r":{"a":0,"k":0,"ix":4},"nm":"Rectangle Path 1","mn":"ADBE Vector Shape - Rect","hd":false},{"ty":"fl","c":{"a":0,"k":[0.898039221764,0.368627458811,0.35686275363,1],"ix":4},"o":{"a":0,"k":100,"ix":5},"r":1,"bm":0,"nm":"Fill 1","mn":"ADBE Vector Graphic - Fill","hd":false},{"ty":"tr","p":{"a":0,"k":[0,0],"ix":2},"a":{"a":0,"k":[0,0],"ix":1},"s":{"a":0,"k":[300,300],"ix":3},"r":{"a":0,"k":45.517,"ix":6},"o":{"a":0,"k":100,"ix":7},"sk":{"a":0,"k":0,"ix":4},"sa":{"a":0,"k":0,"ix":5},"nm":"Transform"}],"nm":"Rectangle 302","np":2,"cix":2,"bm":0,"ix":1,"mn":"ADBE Vector Group","hd":false}],"ip":0,"op":300,"st":0,"bm":0},{"ddd":0,"ind":29,"ty":4,"nm":"Rectangle 301","sr":1,"ks":{"o":{"a":0,"k":100,"ix":11},"r":{"a":1,"k":[{"i":{"x":[0.833],"y":[0.833]},"o":{"x":[0.27],"y":[0]},"t":0,"s":[-326]},{"t":135,"s":[1474]}],"ix":10},"p":{"a":1,"k":[{"i":{"x":0.6,"y":1},"o":{"x":0.167,"y":0.163},"t":43,"s":[1560.922,1738.5,0],"to":[308.667,-39.333,0],"ti":[67.333,-868.667,0]},{"t":102,"s":[2236.922,3374.5,0]}],"ix":2},"a":{"a":0,"k":[0,0,0],"ix":1},"s":{"a":1,"k":[{"i":{"x":[0.4,0.4,0.4],"y":[1,1,1]},"o":{"x":[0.167,0.167,0.167],"y":[0.562,0.562,50.556]},"t":0,"s":[0,0,100]},{"t":91,"s":[90,90,100]}],"ix":6}},"ao":0,"shapes":[{"ty":"gr","it":[{"ty":"rc","d":1,"s":{"a":0,"k":[24,35],"ix":2},"p":{"a":0,"k":[0,0],"ix":3},"r":{"a":0,"k":0,"ix":4},"nm":"Rectangle Path 1","mn":"ADBE Vector Shape - Rect","hd":false},{"ty":"fl","c":{"a":0,"k":[0.964705884457,0.772549033165,0.411764711142,1],"ix":4},"o":{"a":0,"k":100,"ix":5},"r":1,"bm":0,"nm":"Fill 1","mn":"ADBE Vector Graphic - Fill","hd":false},{"ty":"tr","p":{"a":0,"k":[0,0],"ix":2},"a":{"a":0,"k":[0,0],"ix":1},"s":{"a":0,"k":[300,300],"ix":3},"r":{"a":0,"k":45.517,"ix":6},"o":{"a":0,"k":100,"ix":7},"sk":{"a":0,"k":0,"ix":4},"sa":{"a":0,"k":0,"ix":5},"nm":"Transform"}],"nm":"Rectangle 301","np":2,"cix":2,"bm":0,"ix":1,"mn":"ADBE Vector Group","hd":false}],"ip":0,"op":300,"st":0,"bm":0}]}],"layers":[{"ddd":0,"ind":1,"ty":4,"nm":"path 3","sr":1,"ks":{"o":{"a":1,"k":[{"i":{"x":[0.833],"y":[0.833]},"o":{"x":[0.167],"y":[0.167]},"t":0,"s":[0]},{"i":{"x":[0.833],"y":[0.833]},"o":{"x":[0.167],"y":[0.167]},"t":31,"s":[100]},{"i":{"x":[0.833],"y":[0.833]},"o":{"x":[0.167],"y":[0.167]},"t":150,"s":[100]},{"t":165,"s":[0]}],"ix":11},"r":{"a":0,"k":227,"ix":10},"p":{"a":0,"k":[1772,1408,0],"ix":2},"a":{"a":0,"k":[1800,90,0],"ix":1},"s":{"a":0,"k":[96,96,100],"ix":6}},"ao":0,"shapes":[{"ty":"gr","it":[{"ind":0,"ty":"sh","ix":1,"ks":{"a":0,"k":{"i":[[0,0],[33.333,40],[33.333,-40],[33.333,40],[33.333,-40],[33.333,40],[33.333,-40],[33.333,40],[33.333,-40],[33.333,40],[33.333,-40],[33.333,40],[33.333,-40]],"o":[[-33.333,40],[-33.333,-40],[-33.333,40],[-33.333,-40],[-33.333,40],[-33.333,-40],[-33.333,40],[-33.333,-40],[-33.333,40],[-33.333,-40],[-33.333,40],[-33.333,-40],[0,0]],"v":[[600,0],[500,0],[400,0],[300,0],[200,0],[100,0],[0,0],[-100,0],[-200,0],[-300,0],[-400,0],[-500,0],[-600,0]],"c":false},"ix":2},"nm":"Path 1","mn":"ADBE Vector Shape - Group","hd":false},{"ty":"st","c":{"a":0,"k":[0.35686275363,0.662468194962,0.898039221764,1],"ix":3},"o":{"a":0,"k":100,"ix":4},"w":{"a":0,"k":12,"ix":5},"lc":2,"lj":1,"ml":4,"bm":0,"nm":"Stroke 1","mn":"ADBE Vector Graphic - Stroke","hd":false},{"ty":"tr","p":{"a":0,"k":[0,0],"ix":2},"a":{"a":0,"k":[0,0],"ix":1},"s":{"a":0,"k":[300,300],"ix":3},"r":{"a":0,"k":0,"ix":6},"o":{"a":0,"k":100,"ix":7},"sk":{"a":0,"k":0,"ix":4},"sa":{"a":0,"k":0,"ix":5},"nm":"Transform"}],"nm":"path","np":2,"cix":2,"bm":0,"ix":1,"mn":"ADBE Vector Group","hd":false},{"ty":"tm","s":{"a":1,"k":[{"i":{"x":[0.83],"y":[1]},"o":{"x":[0.7],"y":[0]},"t":39,"s":[0]},{"t":105,"s":[73]}],"ix":1},"e":{"a":1,"k":[{"i":{"x":[0.83],"y":[1]},"o":{"x":[0.7],"y":[0]},"t":33,"s":[0]},{"t":98,"s":[100]}],"ix":2},"o":{"a":0,"k":0,"ix":3},"m":1,"ix":2,"nm":"Trim Paths 1","mn":"ADBE Vector Filter - Trim","hd":false}],"ip":0,"op":300,"st":0,"bm":0},{"ddd":0,"ind":2,"ty":4,"nm":"path 2","sr":1,"ks":{"o":{"a":1,"k":[{"i":{"x":[0.833],"y":[0.833]},"o":{"x":[0.167],"y":[0.167]},"t":0,"s":[0]},{"i":{"x":[0.833],"y":[0.833]},"o":{"x":[0.167],"y":[0.167]},"t":31,"s":[100]},{"i":{"x":[0.833],"y":[0.833]},"o":{"x":[0.167],"y":[0.167]},"t":150,"s":[100]},{"t":165,"s":[0]}],"ix":11},"r":{"a":0,"k":157,"ix":10},"p":{"a":0,"k":[1740,1352,0],"ix":2},"a":{"a":0,"k":[1800,90,0],"ix":1},"s":{"a":0,"k":[96,96,100],"ix":6}},"ao":0,"shapes":[{"ty":"gr","it":[{"ind":0,"ty":"sh","ix":1,"ks":{"a":0,"k":{"i":[[0,0],[33.333,40],[33.333,-40],[33.333,40],[33.333,-40],[33.333,40],[33.333,-40],[33.333,40],[33.333,-40],[33.333,40],[33.333,-40],[33.333,40],[33.333,-40]],"o":[[-33.333,40],[-33.333,-40],[-33.333,40],[-33.333,-40],[-33.333,40],[-33.333,-40],[-33.333,40],[-33.333,-40],[-33.333,40],[-33.333,-40],[-33.333,40],[-33.333,-40],[0,0]],"v":[[600,0],[500,0],[400,0],[300,0],[200,0],[100,0],[0,0],[-100,0],[-200,0],[-300,0],[-400,0],[-500,0],[-600,0]],"c":false},"ix":2},"nm":"Path 1","mn":"ADBE Vector Shape - Group","hd":false},{"ty":"st","c":{"a":0,"k":[0.898039221764,0.81527107954,0.35686275363,1],"ix":3},"o":{"a":0,"k":100,"ix":4},"w":{"a":0,"k":12,"ix":5},"lc":2,"lj":1,"ml":4,"bm":0,"nm":"Stroke 1","mn":"ADBE Vector Graphic - Stroke","hd":false},{"ty":"tr","p":{"a":0,"k":[0,0],"ix":2},"a":{"a":0,"k":[0,0],"ix":1},"s":{"a":0,"k":[300,300],"ix":3},"r":{"a":0,"k":0,"ix":6},"o":{"a":0,"k":100,"ix":7},"sk":{"a":0,"k":0,"ix":4},"sa":{"a":0,"k":0,"ix":5},"nm":"Transform"}],"nm":"path","np":2,"cix":2,"bm":0,"ix":1,"mn":"ADBE Vector Group","hd":false},{"ty":"tm","s":{"a":1,"k":[{"i":{"x":[0.83],"y":[1]},"o":{"x":[0.7],"y":[0]},"t":9,"s":[0]},{"t":87,"s":[73]}],"ix":1},"e":{"a":1,"k":[{"i":{"x":[0.83],"y":[1]},"o":{"x":[0.7],"y":[0]},"t":3,"s":[0]},{"t":80,"s":[100]}],"ix":2},"o":{"a":0,"k":0,"ix":3},"m":1,"ix":2,"nm":"Trim Paths 1","mn":"ADBE Vector Filter - Trim","hd":false}],"ip":0,"op":300,"st":0,"bm":0},{"ddd":0,"ind":3,"ty":4,"nm":"path","sr":1,"ks":{"o":{"a":1,"k":[{"i":{"x":[0.833],"y":[0.833]},"o":{"x":[0.167],"y":[0.167]},"t":0,"s":[0]},{"i":{"x":[0.833],"y":[0.833]},"o":{"x":[0.167],"y":[0.167]},"t":31,"s":[100]},{"i":{"x":[0.833],"y":[0.833]},"o":{"x":[0.167],"y":[0.167]},"t":150,"s":[100]},{"t":165,"s":[0]}],"ix":11},"r":{"a":0,"k":35,"ix":10},"p":{"a":0,"k":[1644,1416,0],"ix":2},"a":{"a":0,"k":[1800,90,0],"ix":1},"s":{"a":0,"k":[96,96,100],"ix":6}},"ao":0,"shapes":[{"ty":"gr","it":[{"ind":0,"ty":"sh","ix":1,"ks":{"a":0,"k":{"i":[[0,0],[33.333,40],[33.333,-40],[33.333,40],[33.333,-40],[33.333,40],[33.333,-40],[33.333,40],[33.333,-40],[33.333,40],[33.333,-40],[33.333,40],[33.333,-40]],"o":[[-33.333,40],[-33.333,-40],[-33.333,40],[-33.333,-40],[-33.333,40],[-33.333,-40],[-33.333,40],[-33.333,-40],[-33.333,40],[-33.333,-40],[-33.333,40],[-33.333,-40],[0,0]],"v":[[600,0],[500,0],[400,0],[300,0],[200,0],[100,0],[0,0],[-100,0],[-200,0],[-300,0],[-400,0],[-500,0],[-600,0]],"c":false},"ix":2},"nm":"Path 1","mn":"ADBE Vector Shape - Group","hd":false},{"ty":"st","c":{"a":0,"k":[0.898039221764,0.368627458811,0.35686275363,1],"ix":3},"o":{"a":0,"k":100,"ix":4},"w":{"a":0,"k":12,"ix":5},"lc":2,"lj":1,"ml":4,"bm":0,"nm":"Stroke 1","mn":"ADBE Vector Graphic - Stroke","hd":false},{"ty":"tr","p":{"a":0,"k":[0,0],"ix":2},"a":{"a":0,"k":[0,0],"ix":1},"s":{"a":0,"k":[300,300],"ix":3},"r":{"a":0,"k":0,"ix":6},"o":{"a":0,"k":100,"ix":7},"sk":{"a":0,"k":0,"ix":4},"sa":{"a":0,"k":0,"ix":5},"nm":"Transform"}],"nm":"path","np":2,"cix":2,"bm":0,"ix":1,"mn":"ADBE Vector Group","hd":false},{"ty":"tm","s":{"a":1,"k":[{"i":{"x":[0.83],"y":[1]},"o":{"x":[0.7],"y":[0]},"t":9,"s":[0]},{"t":134,"s":[73]}],"ix":1},"e":{"a":1,"k":[{"i":{"x":[0.83],"y":[1]},"o":{"x":[0.7],"y":[0]},"t":3,"s":[0]},{"t":127,"s":[100]}],"ix":2},"o":{"a":0,"k":0,"ix":3},"m":1,"ix":2,"nm":"Trim Paths 1","mn":"ADBE Vector Filter - Trim","hd":false}],"ip":0,"op":300,"st":0,"bm":0},{"ddd":0,"ind":4,"ty":4,"nm":"Vector 5","sr":1,"ks":{"o":{"a":1,"k":[{"i":{"x":[0.833],"y":[0.833]},"o":{"x":[0.167],"y":[0.167]},"t":150,"s":[100]},{"t":165,"s":[0]}],"ix":11},"r":{"a":0,"k":0,"ix":10},"p":{"a":0,"k":[1765.906,1760.499,0],"ix":2},"a":{"a":0,"k":[0,0,0],"ix":1},"s":{"a":0,"k":[0,0,100],"ix":6}},"ao":0,"shapes":[{"ty":"gr","it":[{"ind":0,"ty":"sh","ix":1,"ks":{"a":0,"k":{"i":[[0,0],[0,-16.797],[10.721,15.486]],"o":[[-63.614,-43.6],[0,24.467],[0,0]],"v":[[35.738,29.663],[20.728,-8.577],[-35.738,-29.663]],"c":false},"ix":2},"nm":"Path 1","mn":"ADBE Vector Shape - Group","hd":false},{"ty":"st","c":{"a":0,"k":[0.964705884457,0.772549033165,0.411764711142,1],"ix":3},"o":{"a":0,"k":100,"ix":4},"w":{"a":0,"k":7.59,"ix":5},"lc":2,"lj":2,"bm":0,"nm":"Stroke 1","mn":"ADBE Vector Graphic - Stroke","hd":false},{"ty":"tr","p":{"a":0,"k":[0,0],"ix":2},"a":{"a":0,"k":[0,0],"ix":1},"s":{"a":0,"k":[300,300],"ix":3},"r":{"a":0,"k":21,"ix":6},"o":{"a":0,"k":100,"ix":7},"sk":{"a":0,"k":0,"ix":4},"sa":{"a":0,"k":0,"ix":5},"nm":"Transform"}],"nm":"Vector 1","np":2,"cix":2,"bm":0,"ix":1,"mn":"ADBE Vector Group","hd":false}],"ip":0,"op":300,"st":0,"bm":0},{"ddd":0,"ind":5,"ty":4,"nm":"Vector 1","sr":1,"ks":{"o":{"a":1,"k":[{"i":{"x":[0.833],"y":[0.833]},"o":{"x":[0.167],"y":[0.167]},"t":150,"s":[100]},{"t":165,"s":[0]}],"ix":11},"r":{"a":0,"k":0,"ix":10},"p":{"a":0,"k":[1717.961,1766.218,0],"ix":2},"a":{"a":0,"k":[0,0,0],"ix":1},"s":{"a":0,"k":[0,0,100],"ix":6}},"ao":0,"shapes":[{"ty":"gr","it":[{"ind":0,"ty":"sh","ix":1,"ks":{"a":0,"k":{"i":[[0,0],[0,-13.675],[8.729,12.608]],"o":[[-51.792,-35.498],[0,19.92],[0,0]],"v":[[29.096,24.15],[16.876,-6.983],[-29.096,-24.15]],"c":false},"ix":2},"nm":"Path 1","mn":"ADBE Vector Shape - Group","hd":false},{"ty":"st","c":{"a":0,"k":[0.964705884457,0.772549033165,0.411764711142,1],"ix":3},"o":{"a":0,"k":100,"ix":4},"w":{"a":0,"k":7.59,"ix":5},"lc":2,"lj":2,"bm":0,"nm":"Stroke 1","mn":"ADBE Vector Graphic - Stroke","hd":false},{"ty":"tr","p":{"a":0,"k":[0,0],"ix":2},"a":{"a":0,"k":[0,0],"ix":1},"s":{"a":0,"k":[300,300],"ix":3},"r":{"a":0,"k":-3,"ix":6},"o":{"a":0,"k":100,"ix":7},"sk":{"a":0,"k":0,"ix":4},"sa":{"a":0,"k":0,"ix":5},"nm":"Transform"}],"nm":"Vector 1","np":2,"cix":2,"bm":0,"ix":1,"mn":"ADBE Vector Group","hd":false}],"ip":0,"op":300,"st":0,"bm":0},{"ddd":0,"ind":6,"ty":4,"nm":"Vector 4","sr":1,"ks":{"o":{"a":1,"k":[{"i":{"x":[0.833],"y":[0.833]},"o":{"x":[0.167],"y":[0.167]},"t":150,"s":[100]},{"t":165,"s":[0]}],"ix":11},"r":{"a":0,"k":0,"ix":10},"p":{"a":0,"k":[1633.214,1733.089,0],"ix":2},"a":{"a":0,"k":[0,0,0],"ix":1},"s":{"a":0,"k":[0,0,100],"ix":6}},"ao":0,"shapes":[{"ty":"gr","it":[{"ind":0,"ty":"sh","ix":1,"ks":{"a":0,"k":{"i":[[0,0],[0,-11.446],[7.306,10.553]],"o":[[-43.347,-29.71],[0,16.672],[0,0]],"v":[[24.352,20.212],[14.124,-5.845],[-24.352,-20.212]],"c":false},"ix":2},"nm":"Path 1","mn":"ADBE Vector Shape - Group","hd":false},{"ty":"st","c":{"a":0,"k":[0.898039221764,0.368627458811,0.35686275363,1],"ix":3},"o":{"a":0,"k":100,"ix":4},"w":{"a":0,"k":7.59,"ix":5},"lc":2,"lj":2,"bm":0,"nm":"Stroke 1","mn":"ADBE Vector Graphic - Stroke","hd":false},{"ty":"tr","p":{"a":0,"k":[0,0],"ix":2},"a":{"a":0,"k":[0,0],"ix":1},"s":{"a":0,"k":[300,300],"ix":3},"r":{"a":0,"k":58,"ix":6},"o":{"a":0,"k":100,"ix":7},"sk":{"a":0,"k":0,"ix":4},"sa":{"a":0,"k":0,"ix":5},"nm":"Transform"}],"nm":"Vector 3","np":2,"cix":2,"bm":0,"ix":1,"mn":"ADBE Vector Group","hd":false}],"ip":0,"op":300,"st":0,"bm":0},{"ddd":0,"ind":7,"ty":4,"nm":"Vector 3","sr":1,"ks":{"o":{"a":1,"k":[{"i":{"x":[0.833],"y":[0.833]},"o":{"x":[0.167],"y":[0.167]},"t":150,"s":[100]},{"t":165,"s":[0]}],"ix":11},"r":{"a":0,"k":0,"ix":10},"p":{"a":0,"k":[1670.802,1725.75,0],"ix":2},"a":{"a":0,"k":[0,0,0],"ix":1},"s":{"a":0,"k":[0,0,100],"ix":6}},"ao":0,"shapes":[{"ty":"gr","it":[{"ind":0,"ty":"sh","ix":1,"ks":{"a":0,"k":{"i":[[0,0],[0,-14.864],[9.488,13.705]],"o":[[-56.295,-38.584],[0,21.653],[0,0]],"v":[[31.627,26.25],[18.343,-7.59],[-31.627,-26.25]],"c":false},"ix":2},"nm":"Path 1","mn":"ADBE Vector Shape - Group","hd":false},{"ty":"st","c":{"a":0,"k":[0.898039221764,0.368627458811,0.35686275363,1],"ix":3},"o":{"a":0,"k":100,"ix":4},"w":{"a":0,"k":7.59,"ix":5},"lc":2,"lj":2,"bm":0,"nm":"Stroke 1","mn":"ADBE Vector Graphic - Stroke","hd":false},{"ty":"tr","p":{"a":0,"k":[0,0],"ix":2},"a":{"a":0,"k":[0,0],"ix":1},"s":{"a":0,"k":[300,300],"ix":3},"r":{"a":0,"k":0,"ix":6},"o":{"a":0,"k":100,"ix":7},"sk":{"a":0,"k":0,"ix":4},"sa":{"a":0,"k":0,"ix":5},"nm":"Transform"}],"nm":"Vector 3","np":2,"cix":2,"bm":0,"ix":1,"mn":"ADBE Vector Group","hd":false}],"ip":0,"op":300,"st":0,"bm":0},{"ddd":0,"ind":8,"ty":4,"nm":"Vector 2","sr":1,"ks":{"o":{"a":1,"k":[{"i":{"x":[0.833],"y":[0.833]},"o":{"x":[0.167],"y":[0.167]},"t":150,"s":[100]},{"t":165,"s":[0]}],"ix":11},"r":{"a":0,"k":0,"ix":10},"p":{"a":0,"k":[1662.802,1780.75,0],"ix":2},"a":{"a":0,"k":[0,0,0],"ix":1},"s":{"a":0,"k":[0,0,100],"ix":6}},"ao":0,"shapes":[{"ty":"gr","it":[{"ind":0,"ty":"sh","ix":1,"ks":{"a":0,"k":{"i":[[0,0],[0,-14.864],[9.488,13.705]],"o":[[-56.295,-38.584],[0,21.653],[0,0]],"v":[[31.627,26.25],[18.343,-7.59],[-31.627,-26.25]],"c":false},"ix":2},"nm":"Path 1","mn":"ADBE Vector Shape - Group","hd":false},{"ty":"st","c":{"a":0,"k":[0.305882364511,0.596078455448,0.960784316063,1],"ix":3},"o":{"a":0,"k":100,"ix":4},"w":{"a":0,"k":7.59,"ix":5},"lc":2,"lj":2,"bm":0,"nm":"Stroke 1","mn":"ADBE Vector Graphic - Stroke","hd":false},{"ty":"tr","p":{"a":0,"k":[0,0],"ix":2},"a":{"a":0,"k":[0,0],"ix":1},"s":{"a":0,"k":[300,300],"ix":3},"r":{"a":0,"k":0,"ix":6},"o":{"a":0,"k":100,"ix":7},"sk":{"a":0,"k":0,"ix":4},"sa":{"a":0,"k":0,"ix":5},"nm":"Transform"}],"nm":"Vector 2","np":2,"cix":2,"bm":0,"ix":1,"mn":"ADBE Vector Group","hd":false}],"ip":0,"op":300,"st":0,"bm":0},{"ddd":0,"ind":9,"ty":4,"nm":"Rectangle 316","sr":1,"ks":{"o":{"a":1,"k":[{"i":{"x":[0.833],"y":[0.833]},"o":{"x":[0.167],"y":[0.167]},"t":150,"s":[100]},{"t":165,"s":[0]}],"ix":11},"r":{"a":0,"k":1474,"ix":10},"p":{"a":1,"k":[{"i":{"x":0.68,"y":1},"o":{"x":0.167,"y":0.167},"t":0,"s":[2859.839,-414.637,0],"to":[0,5.333,0],"ti":[-4,-617.333,0]},{"i":{"x":0.68,"y":1},"o":{"x":0.7,"y":0},"t":36,"s":[2859.839,-382.637,0],"to":[4,617.333,0],"ti":[-5.333,-633.333,0]},{"i":{"x":0.68,"y":1},"o":{"x":0.167,"y":0},"t":134,"s":[2883.839,3289.363,0],"to":[5.333,633.333,0],"ti":[-1.333,-21.333,0]},{"t":138,"s":[2891.839,3417.363,0]}],"ix":2},"a":{"a":0,"k":[0,0,0],"ix":1},"s":{"a":0,"k":[100,100,100],"ix":6}},"ao":0,"shapes":[{"ty":"gr","it":[{"ty":"rc","d":1,"s":{"a":0,"k":[27.36,13.368],"ix":2},"p":{"a":0,"k":[0,0],"ix":3},"r":{"a":0,"k":0,"ix":4},"nm":"Rectangle Path 1","mn":"ADBE Vector Shape - Rect","hd":false},{"ty":"fl","c":{"a":0,"k":[0.898039221764,0.368627458811,0.35686275363,1],"ix":4},"o":{"a":0,"k":100,"ix":5},"r":1,"bm":0,"nm":"Fill 1","mn":"ADBE Vector Graphic - Fill","hd":false},{"ty":"tr","p":{"a":0,"k":[0,0],"ix":2},"a":{"a":0,"k":[0,0],"ix":1},"s":{"a":0,"k":[300,300],"ix":3},"r":{"a":0,"k":-42,"ix":6},"o":{"a":0,"k":100,"ix":7},"sk":{"a":0,"k":0,"ix":4},"sa":{"a":0,"k":0,"ix":5},"nm":"Transform"}],"nm":"Rectangle 302","np":2,"cix":2,"bm":0,"ix":1,"mn":"ADBE Vector Group","hd":false}],"ip":0,"op":300,"st":0,"bm":0},{"ddd":0,"ind":10,"ty":4,"nm":"Rectangle 315","sr":1,"ks":{"o":{"a":1,"k":[{"i":{"x":[0.833],"y":[0.833]},"o":{"x":[0.167],"y":[0.167]},"t":150,"s":[100]},{"t":165,"s":[0]}],"ix":11},"r":{"a":0,"k":1474,"ix":10},"p":{"a":1,"k":[{"i":{"x":0.68,"y":1},"o":{"x":0.167,"y":0.167},"t":0,"s":[3081.991,-422.367,0],"to":[0,5.333,0],"ti":[-4,-617.333,0]},{"i":{"x":0.68,"y":1},"o":{"x":0.7,"y":0},"t":36,"s":[3081.991,-390.367,0],"to":[4,617.333,0],"ti":[-5.333,-633.333,0]},{"i":{"x":0.68,"y":1},"o":{"x":0.167,"y":0},"t":128,"s":[3105.991,3281.633,0],"to":[5.333,633.333,0],"ti":[-1.333,-21.333,0]},{"t":138,"s":[3113.991,3409.633,0]}],"ix":2},"a":{"a":0,"k":[0,0,0],"ix":1},"s":{"a":0,"k":[100,100,100],"ix":6}},"ao":0,"shapes":[{"ty":"gr","it":[{"ty":"rc","d":1,"s":{"a":0,"k":[16.394,24.86],"ix":2},"p":{"a":0,"k":[0,0],"ix":3},"r":{"a":0,"k":0,"ix":4},"nm":"Rectangle Path 1","mn":"ADBE Vector Shape - Rect","hd":false},{"ty":"fl","c":{"a":0,"k":[0.305882364511,0.596078455448,0.960784316063,1],"ix":4},"o":{"a":0,"k":100,"ix":5},"r":1,"bm":0,"nm":"Fill 1","mn":"ADBE Vector Graphic - Fill","hd":false},{"ty":"tr","p":{"a":0,"k":[0,0],"ix":2},"a":{"a":0,"k":[0,0],"ix":1},"s":{"a":0,"k":[300,300],"ix":3},"r":{"a":0,"k":66,"ix":6},"o":{"a":0,"k":100,"ix":7},"sk":{"a":0,"k":0,"ix":4},"sa":{"a":0,"k":0,"ix":5},"nm":"Transform"}],"nm":"Rectangle 299","np":2,"cix":2,"bm":0,"ix":1,"mn":"ADBE Vector Group","hd":false}],"ip":0,"op":300,"st":0,"bm":0},{"ddd":0,"ind":11,"ty":4,"nm":"Rectangle 314","sr":1,"ks":{"o":{"a":1,"k":[{"i":{"x":[0.833],"y":[0.833]},"o":{"x":[0.167],"y":[0.167]},"t":150,"s":[100]},{"t":165,"s":[0]}],"ix":11},"r":{"a":0,"k":1474,"ix":10},"p":{"a":1,"k":[{"i":{"x":0.68,"y":1},"o":{"x":0.167,"y":0.167},"t":0,"s":[2665.312,-241.611,0],"to":[0,5.333,0],"ti":[-4,-617.333,0]},{"i":{"x":0.68,"y":1},"o":{"x":0.7,"y":0},"t":36,"s":[2665.312,-209.611,0],"to":[4,617.333,0],"ti":[-5.333,-633.333,0]},{"i":{"x":0.68,"y":1},"o":{"x":0.167,"y":0},"t":124,"s":[2689.312,3462.389,0],"to":[5.333,633.333,0],"ti":[-1.333,-21.333,0]},{"t":138,"s":[2697.312,3590.389,0]}],"ix":2},"a":{"a":0,"k":[0,0,0],"ix":1},"s":{"a":0,"k":[100,100,100],"ix":6}},"ao":0,"shapes":[{"ty":"gr","it":[{"ty":"rc","d":1,"s":{"a":0,"k":[15.574,15.574],"ix":2},"p":{"a":0,"k":[0,0],"ix":3},"r":{"a":0,"k":0,"ix":4},"nm":"Rectangle Path 1","mn":"ADBE Vector Shape - Rect","hd":false},{"ty":"fl","c":{"a":0,"k":[0.572549045086,0.803921580315,0.380392163992,1],"ix":4},"o":{"a":0,"k":100,"ix":5},"r":1,"bm":0,"nm":"Fill 1","mn":"ADBE Vector Graphic - Fill","hd":false},{"ty":"tr","p":{"a":0,"k":[0,0],"ix":2},"a":{"a":0,"k":[0,0],"ix":1},"s":{"a":0,"k":[300,300],"ix":3},"r":{"a":0,"k":79,"ix":6},"o":{"a":0,"k":100,"ix":7},"sk":{"a":0,"k":0,"ix":4},"sa":{"a":0,"k":0,"ix":5},"nm":"Transform"}],"nm":"Rectangle 300","np":2,"cix":2,"bm":0,"ix":1,"mn":"ADBE Vector Group","hd":false}],"ip":0,"op":300,"st":0,"bm":0},{"ddd":0,"ind":12,"ty":4,"nm":"Rectangle 313","sr":1,"ks":{"o":{"a":1,"k":[{"i":{"x":[0.833],"y":[0.833]},"o":{"x":[0.167],"y":[0.167]},"t":150,"s":[100]},{"t":165,"s":[0]}],"ix":11},"r":{"a":0,"k":1474,"ix":10},"p":{"a":1,"k":[{"i":{"x":0.68,"y":1},"o":{"x":0.167,"y":0.167},"t":0,"s":[2286.835,-415.801,0],"to":[0,5.333,0],"ti":[-4,-617.333,0]},{"i":{"x":0.68,"y":1},"o":{"x":0.7,"y":0},"t":36,"s":[2286.835,-383.801,0],"to":[4,617.333,0],"ti":[-5.333,-633.333,0]},{"i":{"x":0.68,"y":1},"o":{"x":0.167,"y":0},"t":132,"s":[2310.835,3288.199,0],"to":[5.333,633.333,0],"ti":[-1.333,-21.333,0]},{"t":138,"s":[2318.835,3416.199,0]}],"ix":2},"a":{"a":0,"k":[0,0,0],"ix":1},"s":{"a":0,"k":[100,100,100],"ix":6}},"ao":0,"shapes":[{"ty":"gr","it":[{"ty":"rc","d":1,"s":{"a":0,"k":[27.6,41.852],"ix":2},"p":{"a":0,"k":[0,0],"ix":3},"r":{"a":0,"k":0,"ix":4},"nm":"Rectangle Path 1","mn":"ADBE Vector Shape - Rect","hd":false},{"ty":"fl","c":{"a":0,"k":[0.305882364511,0.596078455448,0.960784316063,1],"ix":4},"o":{"a":0,"k":100,"ix":5},"r":1,"bm":0,"nm":"Fill 1","mn":"ADBE Vector Graphic - Fill","hd":false},{"ty":"tr","p":{"a":0,"k":[0,0],"ix":2},"a":{"a":0,"k":[0,0],"ix":1},"s":{"a":0,"k":[300,300],"ix":3},"r":{"a":0,"k":33,"ix":6},"o":{"a":0,"k":100,"ix":7},"sk":{"a":0,"k":0,"ix":4},"sa":{"a":0,"k":0,"ix":5},"nm":"Transform"}],"nm":"Rectangle 299","np":2,"cix":2,"bm":0,"ix":1,"mn":"ADBE Vector Group","hd":false}],"ip":0,"op":300,"st":0,"bm":0},{"ddd":0,"ind":13,"ty":4,"nm":"Rectangle 312","sr":1,"ks":{"o":{"a":1,"k":[{"i":{"x":[0.833],"y":[0.833]},"o":{"x":[0.167],"y":[0.167]},"t":150,"s":[100]},{"t":165,"s":[0]}],"ix":11},"r":{"a":0,"k":1474,"ix":10},"p":{"a":1,"k":[{"i":{"x":0.68,"y":1},"o":{"x":0.167,"y":0.167},"t":0,"s":[2902.285,-144.529,0],"to":[0,5.333,0],"ti":[-4,-617.333,0]},{"i":{"x":0.68,"y":1},"o":{"x":0.7,"y":0},"t":36,"s":[2902.285,-112.529,0],"to":[4,617.333,0],"ti":[-5.333,-633.333,0]},{"i":{"x":0.68,"y":1},"o":{"x":0.167,"y":0},"t":115,"s":[2926.285,3559.471,0],"to":[5.333,633.333,0],"ti":[-1.333,-21.333,0]},{"t":138,"s":[2934.285,3687.471,0]}],"ix":2},"a":{"a":0,"k":[0,0,0],"ix":1},"s":{"a":0,"k":[100,100,100],"ix":6}},"ao":0,"shapes":[{"ty":"gr","it":[{"ty":"rc","d":1,"s":{"a":0,"k":[24.931,37.806],"ix":2},"p":{"a":0,"k":[0,0],"ix":3},"r":{"a":0,"k":0,"ix":4},"nm":"Rectangle Path 1","mn":"ADBE Vector Shape - Rect","hd":false},{"ty":"fl","c":{"a":0,"k":[0.305882364511,0.596078455448,0.960784316063,1],"ix":4},"o":{"a":0,"k":100,"ix":5},"r":1,"bm":0,"nm":"Fill 1","mn":"ADBE Vector Graphic - Fill","hd":false},{"ty":"tr","p":{"a":0,"k":[0,0],"ix":2},"a":{"a":0,"k":[0,0],"ix":1},"s":{"a":0,"k":[300,300],"ix":3},"r":{"a":0,"k":-64,"ix":6},"o":{"a":0,"k":100,"ix":7},"sk":{"a":0,"k":0,"ix":4},"sa":{"a":0,"k":0,"ix":5},"nm":"Transform"}],"nm":"Rectangle 299","np":2,"cix":2,"bm":0,"ix":1,"mn":"ADBE Vector Group","hd":false}],"ip":0,"op":300,"st":0,"bm":0},{"ddd":0,"ind":14,"ty":4,"nm":"Rectangle 311","sr":1,"ks":{"o":{"a":1,"k":[{"i":{"x":[0.833],"y":[0.833]},"o":{"x":[0.167],"y":[0.167]},"t":150,"s":[100]},{"t":165,"s":[0]}],"ix":11},"r":{"a":0,"k":1474,"ix":10},"p":{"a":1,"k":[{"i":{"x":0.68,"y":1},"o":{"x":0.167,"y":0.167},"t":0,"s":[3078.54,-270.57,0],"to":[0,5.333,0],"ti":[-4,-617.333,0]},{"i":{"x":0.68,"y":1},"o":{"x":0.7,"y":0},"t":36,"s":[3078.54,-238.57,0],"to":[4,617.333,0],"ti":[-5.333,-633.333,0]},{"i":{"x":0.68,"y":1},"o":{"x":0.167,"y":0},"t":130,"s":[3102.54,3433.43,0],"to":[5.333,633.333,0],"ti":[-1.333,-21.333,0]},{"t":138,"s":[3110.54,3561.43,0]}],"ix":2},"a":{"a":0,"k":[0,0,0],"ix":1},"s":{"a":0,"k":[100,100,100],"ix":6}},"ao":0,"shapes":[{"ty":"gr","it":[{"ty":"rc","d":1,"s":{"a":0,"k":[15.12,15.12],"ix":2},"p":{"a":0,"k":[0,0],"ix":3},"r":{"a":0,"k":0,"ix":4},"nm":"Rectangle Path 1","mn":"ADBE Vector Shape - Rect","hd":false},{"ty":"fl","c":{"a":0,"k":[0.572549045086,0.803921580315,0.380392163992,1],"ix":4},"o":{"a":0,"k":100,"ix":5},"r":1,"bm":0,"nm":"Fill 1","mn":"ADBE Vector Graphic - Fill","hd":false},{"ty":"tr","p":{"a":0,"k":[0,0],"ix":2},"a":{"a":0,"k":[0,0],"ix":1},"s":{"a":0,"k":[300,300],"ix":3},"r":{"a":0,"k":85,"ix":6},"o":{"a":0,"k":100,"ix":7},"sk":{"a":0,"k":0,"ix":4},"sa":{"a":0,"k":0,"ix":5},"nm":"Transform"}],"nm":"Rectangle 300","np":2,"cix":2,"bm":0,"ix":1,"mn":"ADBE Vector Group","hd":false}],"ip":0,"op":300,"st":0,"bm":0},{"ddd":0,"ind":15,"ty":4,"nm":"Rectangle 310","sr":1,"ks":{"o":{"a":1,"k":[{"i":{"x":[0.833],"y":[0.833]},"o":{"x":[0.167],"y":[0.167]},"t":150,"s":[100]},{"t":165,"s":[0]}],"ix":11},"r":{"a":0,"k":1474,"ix":10},"p":{"a":1,"k":[{"i":{"x":0.68,"y":1},"o":{"x":0.167,"y":0.167},"t":0,"s":[2336.922,-285.5,0],"to":[0,5.333,0],"ti":[-5.333,-638.667,0]},{"i":{"x":0.68,"y":1},"o":{"x":0.7,"y":0},"t":36,"s":[2336.922,-253.5,0],"to":[5.333,638.667,0],"ti":[-5.333,-633.333,0]},{"t":138,"s":[2368.922,3546.5,0]}],"ix":2},"a":{"a":0,"k":[0,0,0],"ix":1},"s":{"a":0,"k":[100,100,100],"ix":6}},"ao":0,"shapes":[{"ty":"gr","it":[{"ty":"rc","d":1,"s":{"a":0,"k":[24,35],"ix":2},"p":{"a":0,"k":[0,0],"ix":3},"r":{"a":0,"k":0,"ix":4},"nm":"Rectangle Path 1","mn":"ADBE Vector Shape - Rect","hd":false},{"ty":"fl","c":{"a":0,"k":[0.964705884457,0.772549033165,0.411764711142,1],"ix":4},"o":{"a":0,"k":100,"ix":5},"r":1,"bm":0,"nm":"Fill 1","mn":"ADBE Vector Graphic - Fill","hd":false},{"ty":"tr","p":{"a":0,"k":[0,0],"ix":2},"a":{"a":0,"k":[0,0],"ix":1},"s":{"a":0,"k":[300,300],"ix":3},"r":{"a":0,"k":45.517,"ix":6},"o":{"a":0,"k":100,"ix":7},"sk":{"a":0,"k":0,"ix":4},"sa":{"a":0,"k":0,"ix":5},"nm":"Transform"}],"nm":"Rectangle 301","np":2,"cix":2,"bm":0,"ix":1,"mn":"ADBE Vector Group","hd":false}],"ip":0,"op":300,"st":0,"bm":0},{"ddd":0,"ind":16,"ty":4,"nm":"Rectangle 309","sr":1,"ks":{"o":{"a":1,"k":[{"i":{"x":[0.833],"y":[0.833]},"o":{"x":[0.167],"y":[0.167]},"t":150,"s":[100]},{"t":165,"s":[0]}],"ix":11},"r":{"a":0,"k":1474,"ix":10},"p":{"a":1,"k":[{"i":{"x":0.68,"y":1},"o":{"x":0.167,"y":0.167},"t":0,"s":[707.839,-502.637,0],"to":[0,5.333,0],"ti":[-4,-617.333,0]},{"i":{"x":0.68,"y":1},"o":{"x":0.7,"y":0},"t":36,"s":[707.839,-470.637,0],"to":[4,617.333,0],"ti":[-5.333,-633.333,0]},{"i":{"x":0.68,"y":1},"o":{"x":0.167,"y":0},"t":122,"s":[731.839,3201.363,0],"to":[5.333,633.333,0],"ti":[-1.333,-21.333,0]},{"t":138,"s":[739.839,3329.363,0]}],"ix":2},"a":{"a":0,"k":[0,0,0],"ix":1},"s":{"a":0,"k":[100,100,100],"ix":6}},"ao":0,"shapes":[{"ty":"gr","it":[{"ty":"rc","d":1,"s":{"a":0,"k":[27.36,13.368],"ix":2},"p":{"a":0,"k":[0,0],"ix":3},"r":{"a":0,"k":0,"ix":4},"nm":"Rectangle Path 1","mn":"ADBE Vector Shape - Rect","hd":false},{"ty":"fl","c":{"a":0,"k":[0.898039221764,0.368627458811,0.35686275363,1],"ix":4},"o":{"a":0,"k":100,"ix":5},"r":1,"bm":0,"nm":"Fill 1","mn":"ADBE Vector Graphic - Fill","hd":false},{"ty":"tr","p":{"a":0,"k":[0,0],"ix":2},"a":{"a":0,"k":[0,0],"ix":1},"s":{"a":0,"k":[300,300],"ix":3},"r":{"a":0,"k":-42,"ix":6},"o":{"a":0,"k":100,"ix":7},"sk":{"a":0,"k":0,"ix":4},"sa":{"a":0,"k":0,"ix":5},"nm":"Transform"}],"nm":"Rectangle 302","np":2,"cix":2,"bm":0,"ix":1,"mn":"ADBE Vector Group","hd":false}],"ip":0,"op":300,"st":0,"bm":0},{"ddd":0,"ind":17,"ty":4,"nm":"Rectangle 308","sr":1,"ks":{"o":{"a":1,"k":[{"i":{"x":[0.833],"y":[0.833]},"o":{"x":[0.167],"y":[0.167]},"t":150,"s":[100]},{"t":165,"s":[0]}],"ix":11},"r":{"a":0,"k":1474,"ix":10},"p":{"a":1,"k":[{"i":{"x":0.68,"y":1},"o":{"x":0.167,"y":0.167},"t":0,"s":[929.991,-510.367,0],"to":[0,5.333,0],"ti":[-4,-617.333,0]},{"i":{"x":0.68,"y":1},"o":{"x":0.7,"y":0},"t":36,"s":[929.991,-478.367,0],"to":[4,617.333,0],"ti":[-5.333,-633.333,0]},{"i":{"x":0.68,"y":1},"o":{"x":0.167,"y":0},"t":135,"s":[953.991,3193.633,0],"to":[5.333,633.333,0],"ti":[-1.333,-21.333,0]},{"t":138,"s":[961.991,3321.633,0]}],"ix":2},"a":{"a":0,"k":[0,0,0],"ix":1},"s":{"a":0,"k":[100,100,100],"ix":6}},"ao":0,"shapes":[{"ty":"gr","it":[{"ty":"rc","d":1,"s":{"a":0,"k":[16.394,24.86],"ix":2},"p":{"a":0,"k":[0,0],"ix":3},"r":{"a":0,"k":0,"ix":4},"nm":"Rectangle Path 1","mn":"ADBE Vector Shape - Rect","hd":false},{"ty":"fl","c":{"a":0,"k":[0.305882364511,0.596078455448,0.960784316063,1],"ix":4},"o":{"a":0,"k":100,"ix":5},"r":1,"bm":0,"nm":"Fill 1","mn":"ADBE Vector Graphic - Fill","hd":false},{"ty":"tr","p":{"a":0,"k":[0,0],"ix":2},"a":{"a":0,"k":[0,0],"ix":1},"s":{"a":0,"k":[300,300],"ix":3},"r":{"a":0,"k":66,"ix":6},"o":{"a":0,"k":100,"ix":7},"sk":{"a":0,"k":0,"ix":4},"sa":{"a":0,"k":0,"ix":5},"nm":"Transform"}],"nm":"Rectangle 299","np":2,"cix":2,"bm":0,"ix":1,"mn":"ADBE Vector Group","hd":false}],"ip":0,"op":300,"st":0,"bm":0},{"ddd":0,"ind":18,"ty":4,"nm":"Rectangle 307","sr":1,"ks":{"o":{"a":1,"k":[{"i":{"x":[0.833],"y":[0.833]},"o":{"x":[0.167],"y":[0.167]},"t":150,"s":[100]},{"t":165,"s":[0]}],"ix":11},"r":{"a":0,"k":1474,"ix":10},"p":{"a":1,"k":[{"i":{"x":0.68,"y":1},"o":{"x":0.167,"y":0.167},"t":0,"s":[1649.639,-241.244,0],"to":[0,5.333,0],"ti":[-4,-617.333,0]},{"i":{"x":0.68,"y":1},"o":{"x":0.7,"y":0},"t":36,"s":[1649.639,-209.244,0],"to":[4,617.333,0],"ti":[-5.333,-633.333,0]},{"i":{"x":0.68,"y":1},"o":{"x":0.167,"y":0},"t":100,"s":[1673.639,3462.756,0],"to":[5.333,633.333,0],"ti":[-1.333,-21.333,0]},{"t":138,"s":[1681.639,3590.756,0]}],"ix":2},"a":{"a":0,"k":[0,0,0],"ix":1},"s":{"a":0,"k":[100,100,100],"ix":6}},"ao":0,"shapes":[{"ty":"gr","it":[{"ty":"rc","d":1,"s":{"a":0,"k":[16.162,7.896],"ix":2},"p":{"a":0,"k":[0,0],"ix":3},"r":{"a":0,"k":0,"ix":4},"nm":"Rectangle Path 1","mn":"ADBE Vector Shape - Rect","hd":false},{"ty":"fl","c":{"a":0,"k":[0.898039221764,0.368627458811,0.35686275363,1],"ix":4},"o":{"a":0,"k":100,"ix":5},"r":1,"bm":0,"nm":"Fill 1","mn":"ADBE Vector Graphic - Fill","hd":false},{"ty":"tr","p":{"a":0,"k":[0,0],"ix":2},"a":{"a":0,"k":[0,0],"ix":1},"s":{"a":0,"k":[300,300],"ix":3},"r":{"a":0,"k":-18,"ix":6},"o":{"a":0,"k":100,"ix":7},"sk":{"a":0,"k":0,"ix":4},"sa":{"a":0,"k":0,"ix":5},"nm":"Transform"}],"nm":"Rectangle 302","np":2,"cix":2,"bm":0,"ix":1,"mn":"ADBE Vector Group","hd":false}],"ip":0,"op":300,"st":0,"bm":0},{"ddd":0,"ind":19,"ty":4,"nm":"Rectangle 306","sr":1,"ks":{"o":{"a":1,"k":[{"i":{"x":[0.833],"y":[0.833]},"o":{"x":[0.167],"y":[0.167]},"t":150,"s":[100]},{"t":165,"s":[0]}],"ix":11},"r":{"a":0,"k":1474,"ix":10},"p":{"a":1,"k":[{"i":{"x":0.68,"y":1},"o":{"x":0.167,"y":0.167},"t":0,"s":[513.312,-329.611,0],"to":[0,5.333,0],"ti":[-4,-617.333,0]},{"i":{"x":0.68,"y":1},"o":{"x":0.7,"y":0},"t":36,"s":[513.312,-297.611,0],"to":[4,617.333,0],"ti":[-5.333,-633.333,0]},{"i":{"x":0.68,"y":1},"o":{"x":0.167,"y":0},"t":124,"s":[537.312,3374.389,0],"to":[5.333,633.333,0],"ti":[-1.333,-21.333,0]},{"t":138,"s":[545.312,3502.389,0]}],"ix":2},"a":{"a":0,"k":[0,0,0],"ix":1},"s":{"a":0,"k":[100,100,100],"ix":6}},"ao":0,"shapes":[{"ty":"gr","it":[{"ty":"rc","d":1,"s":{"a":0,"k":[15.574,15.574],"ix":2},"p":{"a":0,"k":[0,0],"ix":3},"r":{"a":0,"k":0,"ix":4},"nm":"Rectangle Path 1","mn":"ADBE Vector Shape - Rect","hd":false},{"ty":"fl","c":{"a":0,"k":[0.572549045086,0.803921580315,0.380392163992,1],"ix":4},"o":{"a":0,"k":100,"ix":5},"r":1,"bm":0,"nm":"Fill 1","mn":"ADBE Vector Graphic - Fill","hd":false},{"ty":"tr","p":{"a":0,"k":[0,0],"ix":2},"a":{"a":0,"k":[0,0],"ix":1},"s":{"a":0,"k":[300,300],"ix":3},"r":{"a":0,"k":79,"ix":6},"o":{"a":0,"k":100,"ix":7},"sk":{"a":0,"k":0,"ix":4},"sa":{"a":0,"k":0,"ix":5},"nm":"Transform"}],"nm":"Rectangle 300","np":2,"cix":2,"bm":0,"ix":1,"mn":"ADBE Vector Group","hd":false}],"ip":0,"op":300,"st":0,"bm":0},{"ddd":0,"ind":20,"ty":4,"nm":"Rectangle 305","sr":1,"ks":{"o":{"a":1,"k":[{"i":{"x":[0.833],"y":[0.833]},"o":{"x":[0.167],"y":[0.167]},"t":150,"s":[100]},{"t":165,"s":[0]}],"ix":11},"r":{"a":0,"k":1474,"ix":10},"p":{"a":1,"k":[{"i":{"x":0.68,"y":1},"o":{"x":0.167,"y":0.167},"t":0,"s":[134.835,-503.801,0],"to":[0,5.333,0],"ti":[-5.333,-638.667,0]},{"i":{"x":0.68,"y":1},"o":{"x":0.7,"y":0},"t":36,"s":[134.835,-471.801,0],"to":[5.333,638.667,0],"ti":[-5.333,-633.333,0]},{"t":138,"s":[166.835,3328.199,0]}],"ix":2},"a":{"a":0,"k":[0,0,0],"ix":1},"s":{"a":0,"k":[100,100,100],"ix":6}},"ao":0,"shapes":[{"ty":"gr","it":[{"ty":"rc","d":1,"s":{"a":0,"k":[27.6,41.852],"ix":2},"p":{"a":0,"k":[0,0],"ix":3},"r":{"a":0,"k":0,"ix":4},"nm":"Rectangle Path 1","mn":"ADBE Vector Shape - Rect","hd":false},{"ty":"fl","c":{"a":0,"k":[0.305882364511,0.596078455448,0.960784316063,1],"ix":4},"o":{"a":0,"k":100,"ix":5},"r":1,"bm":0,"nm":"Fill 1","mn":"ADBE Vector Graphic - Fill","hd":false},{"ty":"tr","p":{"a":0,"k":[0,0],"ix":2},"a":{"a":0,"k":[0,0],"ix":1},"s":{"a":0,"k":[300,300],"ix":3},"r":{"a":0,"k":33,"ix":6},"o":{"a":0,"k":100,"ix":7},"sk":{"a":0,"k":0,"ix":4},"sa":{"a":0,"k":0,"ix":5},"nm":"Transform"}],"nm":"Rectangle 299","np":2,"cix":2,"bm":0,"ix":1,"mn":"ADBE Vector Group","hd":false}],"ip":0,"op":300,"st":0,"bm":0},{"ddd":0,"ind":21,"ty":4,"nm":"Rectangle 299","sr":1,"ks":{"o":{"a":1,"k":[{"i":{"x":[0.833],"y":[0.833]},"o":{"x":[0.167],"y":[0.167]},"t":150,"s":[100]},{"t":165,"s":[0]}],"ix":11},"r":{"a":0,"k":1474,"ix":10},"p":{"a":1,"k":[{"i":{"x":0.68,"y":1},"o":{"x":0.167,"y":0.167},"t":0,"s":[750.285,-232.529,0],"to":[0,5.333,0],"ti":[-4,-617.333,0]},{"i":{"x":0.68,"y":1},"o":{"x":0.7,"y":0},"t":36,"s":[750.285,-200.529,0],"to":[4,617.333,0],"ti":[-5.333,-633.333,0]},{"i":{"x":0.68,"y":1},"o":{"x":0.167,"y":0},"t":115,"s":[774.285,3471.471,0],"to":[5.333,633.333,0],"ti":[-1.333,-21.333,0]},{"t":138,"s":[782.285,3599.471,0]}],"ix":2},"a":{"a":0,"k":[0,0,0],"ix":1},"s":{"a":0,"k":[100,100,100],"ix":6}},"ao":0,"shapes":[{"ty":"gr","it":[{"ty":"rc","d":1,"s":{"a":0,"k":[24.931,37.806],"ix":2},"p":{"a":0,"k":[0,0],"ix":3},"r":{"a":0,"k":0,"ix":4},"nm":"Rectangle Path 1","mn":"ADBE Vector Shape - Rect","hd":false},{"ty":"fl","c":{"a":0,"k":[0.305882364511,0.596078455448,0.960784316063,1],"ix":4},"o":{"a":0,"k":100,"ix":5},"r":1,"bm":0,"nm":"Fill 1","mn":"ADBE Vector Graphic - Fill","hd":false},{"ty":"tr","p":{"a":0,"k":[0,0],"ix":2},"a":{"a":0,"k":[0,0],"ix":1},"s":{"a":0,"k":[300,300],"ix":3},"r":{"a":0,"k":-64,"ix":6},"o":{"a":0,"k":100,"ix":7},"sk":{"a":0,"k":0,"ix":4},"sa":{"a":0,"k":0,"ix":5},"nm":"Transform"}],"nm":"Rectangle 299","np":2,"cix":2,"bm":0,"ix":1,"mn":"ADBE Vector Group","hd":false}],"ip":0,"op":300,"st":0,"bm":0},{"ddd":0,"ind":22,"ty":4,"nm":"Rectangle 304","sr":1,"ks":{"o":{"a":1,"k":[{"i":{"x":[0.833],"y":[0.833]},"o":{"x":[0.167],"y":[0.167]},"t":150,"s":[100]},{"t":165,"s":[0]}],"ix":11},"r":{"a":0,"k":1474,"ix":10},"p":{"a":1,"k":[{"i":{"x":0.68,"y":1},"o":{"x":0.167,"y":0.167},"t":0,"s":[1945.3,-485.235,0],"to":[0,5.333,0],"ti":[-4,-617.333,0]},{"i":{"x":0.68,"y":1},"o":{"x":0.7,"y":0},"t":36,"s":[1945.3,-453.235,0],"to":[4,617.333,0],"ti":[-5.333,-633.333,0]},{"i":{"x":0.68,"y":1},"o":{"x":0.167,"y":0},"t":128,"s":[1969.3,3218.765,0],"to":[5.333,633.333,0],"ti":[-1.333,-21.333,0]},{"t":138,"s":[1977.3,3346.765,0]}],"ix":2},"a":{"a":0,"k":[0,0,0],"ix":1},"s":{"a":0,"k":[100,100,100],"ix":6}},"ao":0,"shapes":[{"ty":"gr","it":[{"ty":"rc","d":1,"s":{"a":0,"k":[16.56,8.091],"ix":2},"p":{"a":0,"k":[0,0],"ix":3},"r":{"a":0,"k":0,"ix":4},"nm":"Rectangle Path 1","mn":"ADBE Vector Shape - Rect","hd":false},{"ty":"fl","c":{"a":0,"k":[0.898039221764,0.368627458811,0.35686275363,1],"ix":4},"o":{"a":0,"k":100,"ix":5},"r":1,"bm":0,"nm":"Fill 1","mn":"ADBE Vector Graphic - Fill","hd":false},{"ty":"tr","p":{"a":0,"k":[0,0],"ix":2},"a":{"a":0,"k":[0,0],"ix":1},"s":{"a":0,"k":[300,300],"ix":3},"r":{"a":0,"k":-62,"ix":6},"o":{"a":0,"k":100,"ix":7},"sk":{"a":0,"k":0,"ix":4},"sa":{"a":0,"k":0,"ix":5},"nm":"Transform"}],"nm":"Rectangle 302","np":2,"cix":2,"bm":0,"ix":1,"mn":"ADBE Vector Group","hd":false}],"ip":0,"op":300,"st":0,"bm":0},{"ddd":0,"ind":23,"ty":4,"nm":"Rectangle 303","sr":1,"ks":{"o":{"a":1,"k":[{"i":{"x":[0.833],"y":[0.833]},"o":{"x":[0.167],"y":[0.167]},"t":150,"s":[100]},{"t":165,"s":[0]}],"ix":11},"r":{"a":0,"k":1474,"ix":10},"p":{"a":1,"k":[{"i":{"x":0.68,"y":1},"o":{"x":0.167,"y":0.167},"t":0,"s":[1635.278,-446.689,0],"to":[0,5.333,0],"ti":[-5.333,-638.667,0]},{"i":{"x":0.68,"y":1},"o":{"x":0.7,"y":0},"t":36,"s":[1635.278,-414.689,0],"to":[5.333,638.667,0],"ti":[-5.333,-633.333,0]},{"t":138,"s":[1667.278,3385.311,0]}],"ix":2},"a":{"a":0,"k":[0,0,0],"ix":1},"s":{"a":0,"k":[100,100,100],"ix":6}},"ao":0,"shapes":[{"ty":"gr","it":[{"ty":"rc","d":1,"s":{"a":0,"k":[14.4,36],"ix":2},"p":{"a":0,"k":[0,0],"ix":3},"r":{"a":0,"k":0,"ix":4},"nm":"Rectangle Path 1","mn":"ADBE Vector Shape - Rect","hd":false},{"ty":"fl","c":{"a":0,"k":[0.698039233685,0.482352942228,0.905882358551,1],"ix":4},"o":{"a":0,"k":100,"ix":5},"r":1,"bm":0,"nm":"Fill 1","mn":"ADBE Vector Graphic - Fill","hd":false},{"ty":"tr","p":{"a":0,"k":[0,0],"ix":2},"a":{"a":0,"k":[0,0],"ix":1},"s":{"a":0,"k":[300,300],"ix":3},"r":{"a":0,"k":-12,"ix":6},"o":{"a":0,"k":100,"ix":7},"sk":{"a":0,"k":0,"ix":4},"sa":{"a":0,"k":0,"ix":5},"nm":"Transform"}],"nm":"Rectangle 298","np":2,"cix":2,"bm":0,"ix":1,"mn":"ADBE Vector Group","hd":false}],"ip":0,"op":300,"st":0,"bm":0},{"ddd":0,"ind":24,"ty":4,"nm":"Rectangle 302","sr":1,"ks":{"o":{"a":1,"k":[{"i":{"x":[0.833],"y":[0.833]},"o":{"x":[0.167],"y":[0.167]},"t":150,"s":[100]},{"t":165,"s":[0]}],"ix":11},"r":{"a":0,"k":1474,"ix":10},"p":{"a":1,"k":[{"i":{"x":0.68,"y":1},"o":{"x":0.167,"y":0.167},"t":0,"s":[1380.315,-100.715,0],"to":[0,5.333,0],"ti":[-4,-617.333,0]},{"i":{"x":0.68,"y":1},"o":{"x":0.7,"y":0},"t":36,"s":[1380.315,-68.715,0],"to":[4,617.333,0],"ti":[-5.333,-633.333,0]},{"i":{"x":0.68,"y":1},"o":{"x":0.167,"y":0},"t":121,"s":[1404.315,3603.285,0],"to":[5.333,633.333,0],"ti":[-1.333,-21.333,0]},{"t":138,"s":[1412.315,3731.285,0]}],"ix":2},"a":{"a":0,"k":[0,0,0],"ix":1},"s":{"a":0,"k":[100,100,100],"ix":6}},"ao":0,"shapes":[{"ty":"gr","it":[{"ty":"rc","d":1,"s":{"a":0,"k":[17.76,8.677],"ix":2},"p":{"a":0,"k":[0,0],"ix":3},"r":{"a":0,"k":0,"ix":4},"nm":"Rectangle Path 1","mn":"ADBE Vector Shape - Rect","hd":false},{"ty":"fl","c":{"a":0,"k":[0.898039221764,0.368627458811,0.35686275363,1],"ix":4},"o":{"a":0,"k":100,"ix":5},"r":1,"bm":0,"nm":"Fill 1","mn":"ADBE Vector Graphic - Fill","hd":false},{"ty":"tr","p":{"a":0,"k":[0,0],"ix":2},"a":{"a":0,"k":[0,0],"ix":1},"s":{"a":0,"k":[300,300],"ix":3},"r":{"a":0,"k":-87,"ix":6},"o":{"a":0,"k":100,"ix":7},"sk":{"a":0,"k":0,"ix":4},"sa":{"a":0,"k":0,"ix":5},"nm":"Transform"}],"nm":"Rectangle 302","np":2,"cix":2,"bm":0,"ix":1,"mn":"ADBE Vector Group","hd":false}],"ip":0,"op":300,"st":0,"bm":0},{"ddd":0,"ind":25,"ty":4,"nm":"Rectangle 300","sr":1,"ks":{"o":{"a":1,"k":[{"i":{"x":[0.833],"y":[0.833]},"o":{"x":[0.167],"y":[0.167]},"t":150,"s":[100]},{"t":165,"s":[0]}],"ix":11},"r":{"a":0,"k":1474,"ix":10},"p":{"a":1,"k":[{"i":{"x":0.68,"y":1},"o":{"x":0.167,"y":0.167},"t":0,"s":[926.54,-358.57,0],"to":[0,5.333,0],"ti":[-4,-617.333,0]},{"i":{"x":0.68,"y":1},"o":{"x":0.7,"y":0},"t":36,"s":[926.54,-326.57,0],"to":[4,617.333,0],"ti":[-5.333,-633.333,0]},{"i":{"x":0.68,"y":1},"o":{"x":0.167,"y":0},"t":130,"s":[950.54,3345.43,0],"to":[5.333,633.333,0],"ti":[-1.333,-21.333,0]},{"t":138,"s":[958.54,3473.43,0]}],"ix":2},"a":{"a":0,"k":[0,0,0],"ix":1},"s":{"a":0,"k":[100,100,100],"ix":6}},"ao":0,"shapes":[{"ty":"gr","it":[{"ty":"rc","d":1,"s":{"a":0,"k":[15.12,15.12],"ix":2},"p":{"a":0,"k":[0,0],"ix":3},"r":{"a":0,"k":0,"ix":4},"nm":"Rectangle Path 1","mn":"ADBE Vector Shape - Rect","hd":false},{"ty":"fl","c":{"a":0,"k":[0.572549045086,0.803921580315,0.380392163992,1],"ix":4},"o":{"a":0,"k":100,"ix":5},"r":1,"bm":0,"nm":"Fill 1","mn":"ADBE Vector Graphic - Fill","hd":false},{"ty":"tr","p":{"a":0,"k":[0,0],"ix":2},"a":{"a":0,"k":[0,0],"ix":1},"s":{"a":0,"k":[300,300],"ix":3},"r":{"a":0,"k":85,"ix":6},"o":{"a":0,"k":100,"ix":7},"sk":{"a":0,"k":0,"ix":4},"sa":{"a":0,"k":0,"ix":5},"nm":"Transform"}],"nm":"Rectangle 300","np":2,"cix":2,"bm":0,"ix":1,"mn":"ADBE Vector Group","hd":false}],"ip":0,"op":300,"st":0,"bm":0},{"ddd":0,"ind":26,"ty":4,"nm":"Rectangle 298","sr":1,"ks":{"o":{"a":1,"k":[{"i":{"x":[0.833],"y":[0.833]},"o":{"x":[0.167],"y":[0.167]},"t":150,"s":[100]},{"t":165,"s":[0]}],"ix":11},"r":{"a":0,"k":1474,"ix":10},"p":{"a":1,"k":[{"i":{"x":0.68,"y":1},"o":{"x":0.167,"y":0.167},"t":0,"s":[1169.269,-329.554,0],"to":[0,5.333,0],"ti":[-4,-617.333,0]},{"i":{"x":0.68,"y":1},"o":{"x":0.7,"y":0},"t":36,"s":[1169.269,-297.554,0],"to":[4,617.333,0],"ti":[-5.333,-633.333,0]},{"i":{"x":0.68,"y":1},"o":{"x":0.167,"y":0},"t":114,"s":[1193.269,3374.446,0],"to":[5.333,633.333,0],"ti":[-1.333,-21.333,0]},{"t":138,"s":[1201.269,3502.446,0]}],"ix":2},"a":{"a":0,"k":[0,0,0],"ix":1},"s":{"a":0,"k":[100,100,100],"ix":6}},"ao":0,"shapes":[{"ty":"gr","it":[{"ty":"rc","d":1,"s":{"a":0,"k":[23.52,58.8],"ix":2},"p":{"a":0,"k":[0,0],"ix":3},"r":{"a":0,"k":0,"ix":4},"nm":"Rectangle Path 1","mn":"ADBE Vector Shape - Rect","hd":false},{"ty":"fl","c":{"a":0,"k":[0.698039233685,0.482352942228,0.905882358551,1],"ix":4},"o":{"a":0,"k":100,"ix":5},"r":1,"bm":0,"nm":"Fill 1","mn":"ADBE Vector Graphic - Fill","hd":false},{"ty":"tr","p":{"a":0,"k":[0,0],"ix":2},"a":{"a":0,"k":[0,0],"ix":1},"s":{"a":0,"k":[300,300],"ix":3},"r":{"a":0,"k":-4,"ix":6},"o":{"a":0,"k":100,"ix":7},"sk":{"a":0,"k":0,"ix":4},"sa":{"a":0,"k":0,"ix":5},"nm":"Transform"}],"nm":"Rectangle 298","np":2,"cix":2,"bm":0,"ix":1,"mn":"ADBE Vector Group","hd":false}],"ip":0,"op":300,"st":0,"bm":0},{"ddd":0,"ind":27,"ty":4,"nm":"Rectangle 301","sr":1,"ks":{"o":{"a":1,"k":[{"i":{"x":[0.833],"y":[0.833]},"o":{"x":[0.167],"y":[0.167]},"t":150,"s":[100]},{"t":165,"s":[0]}],"ix":11},"r":{"a":0,"k":1474,"ix":10},"p":{"a":1,"k":[{"i":{"x":0.68,"y":1},"o":{"x":0.167,"y":0.167},"t":0,"s":[184.922,-373.5,0],"to":[0,5.333,0],"ti":[-5.333,-638.667,0]},{"i":{"x":0.68,"y":1},"o":{"x":0.7,"y":0},"t":36,"s":[184.922,-341.5,0],"to":[5.333,638.667,0],"ti":[-5.333,-633.333,0]},{"t":138,"s":[216.922,3458.5,0]}],"ix":2},"a":{"a":0,"k":[0,0,0],"ix":1},"s":{"a":0,"k":[100,100,100],"ix":6}},"ao":0,"shapes":[{"ty":"gr","it":[{"ty":"rc","d":1,"s":{"a":0,"k":[24,35],"ix":2},"p":{"a":0,"k":[0,0],"ix":3},"r":{"a":0,"k":0,"ix":4},"nm":"Rectangle Path 1","mn":"ADBE Vector Shape - Rect","hd":false},{"ty":"fl","c":{"a":0,"k":[0.964705884457,0.772549033165,0.411764711142,1],"ix":4},"o":{"a":0,"k":100,"ix":5},"r":1,"bm":0,"nm":"Fill 1","mn":"ADBE Vector Graphic - Fill","hd":false},{"ty":"tr","p":{"a":0,"k":[0,0],"ix":2},"a":{"a":0,"k":[0,0],"ix":1},"s":{"a":0,"k":[300,300],"ix":3},"r":{"a":0,"k":45.517,"ix":6},"o":{"a":0,"k":100,"ix":7},"sk":{"a":0,"k":0,"ix":4},"sa":{"a":0,"k":0,"ix":5},"nm":"Transform"}],"nm":"Rectangle 301","np":2,"cix":2,"bm":0,"ix":1,"mn":"ADBE Vector Group","hd":false}],"ip":0,"op":300,"st":0,"bm":0},{"ddd":0,"ind":28,"ty":0,"nm":"Base","refId":"comp_0","sr":1,"ks":{"o":{"a":1,"k":[{"i":{"x":[0.833],"y":[0.833]},"o":{"x":[0.167],"y":[0.167]},"t":150,"s":[100]},{"t":165,"s":[0]}],"ix":11},"r":{"a":0,"k":0,"ix":10},"p":{"a":0,"k":[1684,1220,0],"ix":2},"a":{"a":0,"k":[1620,1620,0],"ix":1},"s":{"a":0,"k":[100,124.882,100],"ix":6}},"ao":0,"w":3240,"h":3240,"ip":0,"op":300,"st":0,"bm":0}],"markers":[]}